02_rtl/Compare_unit.sv
module Compare_unit(
    input logic [1:0] i_metric_path_0,  // A
    input logic [1:0] i_metric_path_1,  // B
    output logic o_compare_less      
);
    // Correct implementation
    assign o_compare_less = (~i_metric_path_0[0] & ~i_metric_path_0[1]) |
                            (i_metric_path_1[0] & i_metric_path_1[1])   |
                            (~i_metric_path_0[1] & i_metric_path_1[0])  |
                            (~i_metric_path_0[1] & i_metric_path_1[1])  |
                            (~i_metric_path_0[0] & i_metric_path_1[1]);
endmodule

03_verif/COMP/tb_compare.sv
`timescale 10ns/1ps
module tb_compare();

// Signals
logic [1:0] i_metric_path_0, i_metric_path_1;
logic o_compare_less;

// Test variables
integer pass_count = 0;
integer fail_count = 0;
integer test_case = 0;

// Instantiate DUT
Compare_unit dut (
    .i_metric_path_0(i_metric_path_0),
    .i_metric_path_1(i_metric_path_1),
    .o_compare_less(o_compare_less)
);

// Test function
function automatic test(input [1:0] a, input [1:0] b);
    return (a <= b);
endfunction

initial begin
    $dumpfile("tb_compare.vcd");
    $dumpvars(0, tb_compare);
end

// Test stimulus
initial begin
    $display("Starting Compare_unit testbench...");
    $display("=================================");
    
    for (test_case = 1; test_case <= 50; test_case++) begin
        // Generate random inputs
        i_metric_path_0 = $random % 4;
        i_metric_path_1 = $random % 4;
        
        // Wait for propagation
        #10;
        
        // Check result
        if (o_compare_less == test(i_metric_path_0, i_metric_path_1)) begin
            $display("Test case %0d: PASS - Inputs: %b, %b | Output: %b | Expected: %b", 
                    test_case, i_metric_path_0, i_metric_path_1, 
                    o_compare_less, test(i_metric_path_0, i_metric_path_1));
            pass_count++;
        end
        else begin
            $display("Test case %0d: FAIL - Inputs: %b, %b | Output: %b | Expected: %b", 
                    test_case, i_metric_path_0, i_metric_path_1, 
                    o_compare_less, test(i_metric_path_0, i_metric_path_1));
            fail_count++;
        end
    end
    
    // Summary
    $display("\nTest Summary:");
    $display("=============");
    $display("Total tests : %0d", test_case-1);
    $display("Passed      : %0d", pass_count);
    $display("Failed      : %0d", fail_count);
    $display("Pass rate   : %0.2f%%", (real'(pass_count)/(test_case-1))*100);
    
    $finish;
end

endmodule

03_verif/COMP/tb_compare.vcd
$version Generated by VerilatedVcd $end
$timescale 1ps $end
 $scope module TOP $end
  $scope module tb_compare $end
   $var wire 2 # i_metric_path_0 [1:0] $end
   $var wire 2 $ i_metric_path_1 [1:0] $end
   $var wire 1 % o_compare_less $end
   $var wire 32 & pass_count [31:0] $end
   $var wire 32 ' fail_count [31:0] $end
   $var wire 32 ( test_case [31:0] $end
   $scope module dut $end
    $var wire 2 # i_metric_path_0 [1:0] $end
    $var wire 2 $ i_metric_path_1 [1:0] $end
    $var wire 1 % o_compare_less $end
   $upscope $end
  $upscope $end
 $upscope $end
$enddefinitions $end


#0
b00 #
b00 $
1%
b00000000000000000000000000000000 &
b00000000000000000000000000000000 '
b00000000000000000000000000000000 (
#100000
b10 #
0%
b00000000000000000000000000000001 &
b00000000000000000000000000000010 (
#200000
b00 #
1%
b00000000000000000000000000000010 &
b00000000000000000000000000000011 (
#300000
b10 #
0%
b00000000000000000000000000000011 &
b00000000000000000000000000000100 (
#400000
b11 #
b11 $
1%
b00000000000000000000000000000100 &
b00000000000000000000000000000101 (
#500000
b01 #
b01 $
b00000000000000000000000000000101 &
b00000000000000000000000000000110 (
#600000
b10 $
b00000000000000000000000000000110 &
b00000000000000000000000000000111 (
#700000
b10 #
b01 $
0%
b00000000000000000000000000000111 &
b00000000000000000000000000001000 (
#800000
b10 $
1%
b00000000000000000000000000001000 &
b00000000000000000000000000001001 (
#900000
b01 #
b00 $
0%
b00000000000000000000000000001001 &
b00000000000000000000000000001010 (
#1000000
b11 #
b00000000000000000000000000001010 &
b00000000000000000000000000001011 (
#1100000
b10 #
b00000000000000000000000000001011 &
b00000000000000000000000000001100 (
#1200000
b10 $
1%
b00000000000000000000000000001100 &
b00000000000000000000000000001101 (
#1300000
b00000000000000000000000000001101 &
b00000000000000000000000000001110 (
#1400000
b00 #
b00000000000000000000000000001110 &
b00000000000000000000000000001111 (
#1500000
b11 #
b00 $
0%
b00000000000000000000000000001111 &
b00000000000000000000000000010000 (
#1600000
b01 #
b10 $
1%
b00000000000000000000000000010000 &
b00000000000000000000000000010001 (
#1700000
b10 #
b01 $
0%
b00000000000000000000000000010001 &
b00000000000000000000000000010010 (
#1800000
b11 #
b00 $
b00000000000000000000000000010010 &
b00000000000000000000000000010011 (
#1900000
b10 $
b00000000000000000000000000010011 &
b00000000000000000000000000010100 (
#2000000
b01 $
b00000000000000000000000000010100 &
b00000000000000000000000000010101 (
#2100000
b10 #
b11 $
1%
b00000000000000000000000000010101 &
b00000000000000000000000000010110 (
#2200000
b00 $
0%
b00000000000000000000000000010110 &
b00000000000000000000000000010111 (
#2300000
b11 #
b11 $
1%
b00000000000000000000000000010111 &
b00000000000000000000000000011000 (
#2400000
b00 #
b10 $
b00000000000000000000000000011000 &
b00000000000000000000000000011001 (
#2500000
b10 #
b11 $
b00000000000000000000000000011001 &
b00000000000000000000000000011010 (
#2600000
b01 #
b00000000000000000000000000011010 &
b00000000000000000000000000011011 (
#2700000
b11 #
b00 $
0%
b00000000000000000000000000011011 &
b00000000000000000000000000011100 (
#2800000
b01 #
b11 $
1%
b00000000000000000000000000011100 &
b00000000000000000000000000011101 (
#2900000
b11 #
b00 $
0%
b00000000000000000000000000011101 &
b00000000000000000000000000011110 (
#3000000
b01 $
b00000000000000000000000000011110 &
b00000000000000000000000000011111 (
#3100000
b01 #
b10 $
1%
b00000000000000000000000000011111 &
b00000000000000000000000000100000 (
#3200000
b11 $
b00000000000000000000000000100000 &
b00000000000000000000000000100001 (
#3300000
b00 #
b00000000000000000000000000100001 &
b00000000000000000000000000100010 (
#3400000
b01 #
b01 $
b00000000000000000000000000100010 &
b00000000000000000000000000100011 (
#3500000
b00 $
0%
b00000000000000000000000000100011 &
b00000000000000000000000000100100 (
#3600000
b10 #
b10 $
1%
b00000000000000000000000000100100 &
b00000000000000000000000000100101 (
#3700000
b00 #
b00 $
b00000000000000000000000000100101 &
b00000000000000000000000000100110 (
#3800000
b11 #
b01 $
0%
b00000000000000000000000000100110 &
b00000000000000000000000000100111 (
#3900000
b00000000000000000000000000100111 &
b00000000000000000000000000101000 (
#4000000
b01 #
b10 $
1%
b00000000000000000000000000101000 &
b00000000000000000000000000101001 (
#4100000
b11 #
b01 $
0%
b00000000000000000000000000101001 &
b00000000000000000000000000101010 (
#4200000
b00000000000000000000000000101010 &
b00000000000000000000000000101011 (
#4300000
b10 #
b11 $
1%
b00000000000000000000000000101011 &
b00000000000000000000000000101100 (
#4400000
b11 #
b01 $
0%
b00000000000000000000000000101100 &
b00000000000000000000000000101101 (
#4500000
b11 $
1%
b00000000000000000000000000101101 &
b00000000000000000000000000101110 (
#4600000
b10 #
b00000000000000000000000000101110 &
b00000000000000000000000000101111 (
#4700000
b00000000000000000000000000101111 &
b00000000000000000000000000110000 (
#4800000
b11 #
b00000000000000000000000000110000 &
b00000000000000000000000000110001 (
#4900000
b00 #
b10 $
b00000000000000000000000000110001 &
b00000000000000000000000000110010 (
#5000000
b00000000000000000000000000110010 &
b00000000000000000000000000110011 (
