02_rtl/Add_unit.sv
module Add_unit(
    input logic [1:0]       i_BM    ,
    input logic [1:0]       i_PM    ,
    output logic [1:0]      o_PM    
);

assign o_PM[0] = (!i_PM[0]&i_BM[0]) | (i_PM[0]&!i_BM[0]) | 
                 (i_PM[0]&i_BM[1]) | (i_PM[1]&i_BM[0]) | 
                 (i_PM[1]&i_BM[1]);
assign o_PM[1] = (i_PM[1] | i_BM[1]) | (i_PM[0] & i_BM[0]);

endmodule

03_verif/ADD_UNIT/tb_addunit.sv
module tb_addunit();

// Signals
logic [1:0] i_BM, i_PM;
logic [1:0] o_PM;

// Test variables
integer pass_count = 0;
integer fail_count = 0;
integer test_case = 0;

// Instantiate DUT
Add_unit dut (
    .i_BM(i_BM),
    .i_PM(i_PM),
    .o_PM(o_PM)
);

// Reference model function
function automatic [1:0] expected_result(input [1:0] a, input [1:0] b);
    logic [2:0] sum;
    sum = a + b;
    return (sum >= 3) ? 2'b11 : sum[1:0];
endfunction

initial begin
    $dumpfile("tb_addunit.vcd");
    $dumpvars(0, tb_addunit);
end


// Test stimulus
initial begin
    $display("Starting Add_unit testbench...");
    $display("============================");
    
    // Test all possible combinations (exhaustive test)
    for (int i = 0; i < 4; i++) begin
        for (int j = 0; j < 4; j++) begin
            test_case++;
            i_BM = i;
            i_PM = j;
            
            #10; // Wait for propagation
            
            // Check result
            if (o_PM === expected_result(i_BM, i_PM)) begin
                $display("Test case %0d: PASS - Inputs: %b + %b | Output: %b | Expected: %b", 
                        test_case, i_BM, i_PM, o_PM, expected_result(i_BM, i_PM));
                pass_count++;
            end
            else begin
                $display("Test case %0d: FAIL - Inputs: %b + %b | Output: %b | Expected: %b", 
                        test_case, i_BM, i_PM, o_PM, expected_result(i_BM, i_PM));
                fail_count++;
            end
        end
    end
    
    // Additional random tests
    for (int k = 0; k < 34; k++) begin // Total 16 exhaustive + 34 random = 50 tests
        test_case++;
        i_BM = $random % 4;
        i_PM = $random % 4;
        
        #10;
        
        if (o_PM === expected_result(i_BM, i_PM)) begin
            $display("Test case %0d: PASS - Inputs: %b + %b | Output: %b | Expected: %b", 
                    test_case, i_BM, i_PM, o_PM, expected_result(i_BM, i_PM));
            pass_count++;
        end
        else begin
            $display("Test case %0d: FAIL - Inputs: %b + %b | Output: %b | Expected: %b", 
                    test_case, i_BM, i_PM, o_PM, expected_result(i_BM, i_PM));
            fail_count++;
        end
    end
    
    // Summary
    $display("\nTest Summary:");
    $display("=============");
    $display("Total tests : %0d", test_case);
    $display("Passed      : %0d", pass_count);
    $display("Failed      : %0d", fail_count);
    $display("Pass rate   : %0.2f%%", (real'(pass_count)/test_case)*100);
    
    $finish;
end

endmodule

03_verif/ADD_UNIT/tb_addunit.vcd
$version Generated by VerilatedVcd $end
$timescale 1ps $end
 $scope module TOP $end
  $scope module tb_addunit $end
   $var wire 2 # i_BM [1:0] $end
   $var wire 2 $ i_PM [1:0] $end
   $var wire 2 % o_PM [1:0] $end
   $var wire 32 & pass_count [31:0] $end
   $var wire 32 ' fail_count [31:0] $end
   $var wire 32 ( test_case [31:0] $end
   $scope module dut $end
    $var wire 2 # i_BM [1:0] $end
    $var wire 2 $ i_PM [1:0] $end
    $var wire 2 % o_PM [1:0] $end
   $upscope $end
   $scope module unnamedblk1 $end
    $var wire 32 ) i [31:0] $end
    $scope module unnamedblk2 $end
     $var wire 32 * j [31:0] $end
    $upscope $end
   $upscope $end
   $scope module unnamedblk3 $end
    $var wire 32 + k [31:0] $end
   $upscope $end
  $upscope $end
 $upscope $end
$enddefinitions $end


#0
b00 #
b00 $
b00 %
b00000000000000000000000000000000 &
b00000000000000000000000000000000 '
b00000000000000000000000000000001 (
b00000000000000000000000000000000 )
b00000000000000000000000000000000 *
b00000000000000000000000000000000 +
#10
b01 $
b01 %
b00000000000000000000000000000001 &
b00000000000000000000000000000010 (
b00000000000000000000000000000001 *
#20
b10 $
b10 %
b00000000000000000000000000000010 &
b00000000000000000000000000000011 (
b00000000000000000000000000000010 *
#30
b11 $
b11 %
b00000000000000000000000000000011 &
b00000000000000000000000000000100 (
b00000000000000000000000000000011 *
#40
b01 #
b00 $
b01 %
b00000000000000000000000000000100 &
b00000000000000000000000000000101 (
b00000000000000000000000000000001 )
b00000000000000000000000000000100 *
#50
b01 $
b10 %
b00000000000000000000000000000101 &
b00000000000000000000000000000110 (
b00000000000000000000000000000001 *
#60
b10 $
b11 %
b00000000000000000000000000000110 &
b00000000000000000000000000000111 (
b00000000000000000000000000000010 *
#70
b11 $
b00000000000000000000000000000111 &
b00000000000000000000000000001000 (
b00000000000000000000000000000011 *
#80
b10 #
b00 $
b10 %
b00000000000000000000000000001000 &
b00000000000000000000000000001001 (
b00000000000000000000000000000010 )
b00000000000000000000000000000100 *
#90
b01 $
b11 %
b00000000000000000000000000001001 &
b00000000000000000000000000001010 (
b00000000000000000000000000000001 *
#100
b10 $
b00000000000000000000000000001010 &
b00000000000000000000000000001011 (
b00000000000000000000000000000010 *
#110
b11 $
b00000000000000000000000000001011 &
b00000000000000000000000000001100 (
b00000000000000000000000000000011 *
#120
b11 #
b00 $
b00000000000000000000000000001100 &
b00000000000000000000000000001101 (
b00000000000000000000000000000011 )
b00000000000000000000000000000100 *
#130
b01 $
b00000000000000000000000000001101 &
b00000000000000000000000000001110 (
b00000000000000000000000000000001 *
#140
b10 $
b00000000000000000000000000001110 &
b00000000000000000000000000001111 (
b00000000000000000000000000000010 *
#150
b11 $
b00000000000000000000000000001111 &
b00000000000000000000000000010000 (
b00000000000000000000000000000011 *
#160
b00 #
b00 $
b00 %
b00000000000000000000000000010000 &
b00000000000000000000000000010001 (
b00000000000000000000000000000100 )
b00000000000000000000000000000100 *
#170
b10 #
b10 %
b00000000000000000000000000010001 &
b00000000000000000000000000010010 (
b00000000000000000000000000000001 +
#180
b00 #
b00 %
b00000000000000000000000000010010 &
b00000000000000000000000000010011 (
b00000000000000000000000000000010 +
#190
b10 #
b10 %
b00000000000000000000000000010011 &
b00000000000000000000000000010100 (
b00000000000000000000000000000011 +
#200
b11 #
b11 $
b11 %
b00000000000000000000000000010100 &
b00000000000000000000000000010101 (
b00000000000000000000000000000100 +
#210
b01 #
b01 $
b10 %
b00000000000000000000000000010101 &
b00000000000000000000000000010110 (
b00000000000000000000000000000101 +
#220
b10 $
b11 %
b00000000000000000000000000010110 &
b00000000000000000000000000010111 (
b00000000000000000000000000000110 +
#230
b10 #
b01 $
b00000000000000000000000000010111 &
b00000000000000000000000000011000 (
b00000000000000000000000000000111 +
#240
b10 $
b00000000000000000000000000011000 &
b00000000000000000000000000011001 (
b00000000000000000000000000001000 +
#250
b01 #
b00 $
b01 %
b00000000000000000000000000011001 &
b00000000000000000000000000011010 (
b00000000000000000000000000001001 +
#260
b11 #
b11 %
b00000000000000000000000000011010 &
b00000000000000000000000000011011 (
b00000000000000000000000000001010 +
#270
b10 #
b10 %
b00000000000000000000000000011011 &
b00000000000000000000000000011100 (
b00000000000000000000000000001011 +
#280
b10 $
b11 %
b00000000000000000000000000011100 &
b00000000000000000000000000011101 (
b00000000000000000000000000001100 +
#290
b00000000000000000000000000011101 &
b00000000000000000000000000011110 (
b00000000000000000000000000001101 +
#300
b00 #
b10 %
b00000000000000000000000000011110 &
b00000000000000000000000000011111 (
b00000000000000000000000000001110 +
#310
b11 #
b00 $
b11 %
b00000000000000000000000000011111 &
b00000000000000000000000000100000 (
b00000000000000000000000000001111 +
#320
b01 #
b10 $
b00000000000000000000000000100000 &
b00000000000000000000000000100001 (
b00000000000000000000000000010000 +
#330
b10 #
b01 $
b00000000000000000000000000100001 &
b00000000000000000000000000100010 (
b00000000000000000000000000010001 +
#340
b11 #
b00 $
b00000000000000000000000000100010 &
b00000000000000000000000000100011 (
b00000000000000000000000000010010 +
#350
b10 $
b00000000000000000000000000100011 &
b00000000000000000000000000100100 (
b00000000000000000000000000010011 +
#360
b01 $
b00000000000000000000000000100100 &
b00000000000000000000000000100101 (
b00000000000000000000000000010100 +
#370
b10 #
b11 $
b00000000000000000000000000100101 &
b00000000000000000000000000100110 (
b00000000000000000000000000010101 +
#380
b00 $
b10 %
b00000000000000000000000000100110 &
b00000000000000000000000000100111 (
b00000000000000000000000000010110 +
#390
b11 #
b11 $
b11 %
b00000000000000000000000000100111 &
b00000000000000000000000000101000 (
b00000000000000000000000000010111 +
#400
b00 #
b10 $
b10 %
b00000000000000000000000000101000 &
b00000000000000000000000000101001 (
b00000000000000000000000000011000 +
#410
b10 #
b11 $
b11 %
b00000000000000000000000000101001 &
b00000000000000000000000000101010 (
b00000000000000000000000000011001 +
#420
b01 #
b00000000000000000000000000101010 &
b00000000000000000000000000101011 (
b00000000000000000000000000011010 +
#430
b11 #
b00 $
b00000000000000000000000000101011 &
b00000000000000000000000000101100 (
b00000000000000000000000000011011 +
#440
b01 #
b11 $
b00000000000000000000000000101100 &
b00000000000000000000000000101101 (
b00000000000000000000000000011100 +
#450
b11 #
b00 $
b00000000000000000000000000101101 &
b00000000000000000000000000101110 (
b00000000000000000000000000011101 +
#460
b01 $
b00000000000000000000000000101110 &
b00000000000000000000000000101111 (
b00000000000000000000000000011110 +
#470
b01 #
b10 $
b00000000000000000000000000101111 &
b00000000000000000000000000110000 (
b00000000000000000000000000011111 +
#480
b11 $
b00000000000000000000000000110000 &
b00000000000000000000000000110001 (
b00000000000000000000000000100000 +
#490
b00 #
b00000000000000000000000000110001 &
b00000000000000000000000000110010 (
b00000000000000000000000000100001 +
#500
b00000000000000000000000000110010 &
b00000000000000000000000000100010 +
