02_rtl/Add_unit.sv
module Add_unit(
    input logic [1:0]       i_BM    ,
    input logic [1:0]       i_PM    ,
    output logic [1:0]      o_PM    
);

// | A  | B  | S  |
// | 00 | 00 | 00 |
// | 00 | 01 | 01 |
// | 00 | 10 | 10 |
// | 00 | 11 | 11 |
// | 01 | 00 | 01 |
// | 01 | 01 | 10 |
// | 01 | 10 | 11 |
// | 01 | 11 | 11 |
// | 10 | 00 | 10 |
// | 10 | 01 | 11 |
// | 10 | 10 | 11 |
// | 10 | 11 | 11 |
// | 11 | 00 | 11 |
// | 11 | 01 | 11 |
// | 11 | 10 | 11 |
// | 11 | 11 | 11 |

assign o_PM[0] = (!i_PM[0]&i_BM[0]) | (i_PM[0]&!i_BM[0]) | 
                 (i_PM[0]&i_BM[1]) | (i_PM[1]&i_BM[0])   | 
                 (i_PM[1]&i_BM[1]);
assign o_PM[1] = (i_PM[1] | i_BM[1]) | (i_PM[0] & i_BM[0]);

endmodule

03_verif/ADD_UNIT/tb_addunit.sv
// module tb_addunit();

// // Signals
// logic [1:0] i_BM, i_PM;
// logic [1:0] o_PM;

// // Test variables
// integer pass_count = 0;
// integer fail_count = 0;
// integer test_case = 0;

// // Instantiate DUT
// Add_unit dut (
//     .i_BM(i_BM),
//     .i_PM(i_PM),
//     .o_PM(o_PM)
// );

// // Reference model function
// function automatic [1:0] expected_result(input [1:0] a, input [1:0] b);
//     logic [2:0] sum;
//     sum = a + b;
//     return (sum >= 3) ? 2'b11 : sum[1:0];
// endfunction

// initial begin
//     $dumpfile("tb_addunit.vcd");
//     $dumpvars(0, tb_addunit);
// end


// // Test stimulus
// initial begin
//     $display("Starting Add_unit testbench...");
//     $display("============================");
    
//     // Test all possible combinations (exhaustive test)
//     for (int i = 0; i < 4; i++) begin
//         for (int j = 0; j < 4; j++) begin
//             test_case++;
//             i_BM = i;
//             i_PM = j;
            
//             #10; // Wait for propagation
            
//             // Check result
//             if (o_PM === expected_result(i_BM, i_PM)) begin
//                 $display("Test case %0d: PASS - Inputs: %b + %b | Output: %b | Expected: %b", 
//                         test_case, i_BM, i_PM, o_PM, expected_result(i_BM, i_PM));
//                 pass_count++;
//             end
//             else begin
//                 $display("Test case %0d: FAIL - Inputs: %b + %b | Output: %b | Expected: %b", 
//                         test_case, i_BM, i_PM, o_PM, expected_result(i_BM, i_PM));
//                 fail_count++;
//             end
//         end
//     end
    
//     // Additional random tests
//     for (int k = 0; k < 34; k++) begin // Total 16 exhaustive + 34 random = 50 tests
//         test_case++;
//         i_BM = $random % 4;
//         i_PM = $random % 4;
        
//         #10;
        
//         if (o_PM === expected_result(i_BM, i_PM)) begin
//             $display("Test case %0d: PASS - Inputs: %b + %b | Output: %b | Expected: %b", 
//                     test_case, i_BM, i_PM, o_PM, expected_result(i_BM, i_PM));
//             pass_count++;
//         end
//         else begin
//             $display("Test case %0d: FAIL - Inputs: %b + %b | Output: %b | Expected: %b", 
//                     test_case, i_BM, i_PM, o_PM, expected_result(i_BM, i_PM));
//             fail_count++;
//         end
//     end
    
//     // Summary
//     $display("\nTest Summary:");
//     $display("=============");
//     $display("Total tests : %0d", test_case);
//     $display("Passed      : %0d", pass_count);
//     $display("Failed      : %0d", fail_count);
//     $display("Pass rate   : %0.2f%%", (real'(pass_count)/test_case)*100);
    
//     $finish;
// end

// endmodule
`timescale 1ns/1ps
module tb_addunit();

// Signals
logic [1:0] i_BM, i_PM;
logic [1:0] o_PM;

// Test variables
integer pass_count = 0;
integer fail_count = 0;
integer test_case = 0;

// Instantiate DUT
Add_unit dut (
    .i_BM(i_BM),
    .i_PM(i_PM),
    .o_PM(o_PM)
);

// Task to test a single input combination
function automatic [1:0] expected_result(input [1:0] a, input [1:0] b);
    logic [2:0] sum;
    sum = a + b;
    return (sum >= 3) ? 2'b11 : sum[1:0];
endfunction
task automatic test_add(
    input [1:0] a, b,
    input [1:0] expected
);
    i_BM = a;
    i_PM = b;
    #10; // Wait for propagation
    test_case++;
    if (o_PM === expected) begin
        $display("Test case %0d \t| Inputs: %b + %b \t| Output: %b \t| Expected: %b \t| -> PASS", 
                 test_case, a, b, o_PM, expected);
        pass_count++;
    end else begin
        $display("Test case %0d \t| Inputs: %b + %b \t| Output: %b \t| Expected: %b \t| -> FAIL", 
                 test_case, a, b, o_PM, expected);
        fail_count++;
    end
endtask

// VCD dump
initial begin
    $dumpfile("tb_addunit.vcd");
    $dumpvars(0, tb_addunit);
end

// Test stimulus
initial begin
    $display("Starting Add_unit testbench...");
    $display("============================");
    
    // Test all combinations from the truth table
    test_add(2'b00, 2'b00, expected_result(2'b00, 2'b00)); // A=00, B=00, S=00
    test_add(2'b00, 2'b01, expected_result(2'b00, 2'b01)); // A=00, B=01, S=01
    test_add(2'b00, 2'b10, expected_result(2'b00, 2'b10)); // A=00, B=10, S=10
    test_add(2'b00, 2'b11, expected_result(2'b00, 2'b11)); // A=00, B=11, S=11
    test_add(2'b01, 2'b00, expected_result(2'b01, 2'b00)); // A=01, B=00, S=01
    test_add(2'b01, 2'b01, expected_result(2'b01, 2'b01)); // A=01, B=01, S=10
    test_add(2'b01, 2'b10, expected_result(2'b01, 2'b10)); // A=01, B=10, S=11
    test_add(2'b01, 2'b11, expected_result(2'b01, 2'b11)); // A=01, B=11, S=11
    test_add(2'b10, 2'b00, expected_result(2'b10, 2'b00)); // A=10, B=00, S=10
    test_add(2'b10, 2'b01, expected_result(2'b10, 2'b01)); // A=10, B=01, S=11
    test_add(2'b10, 2'b10, expected_result(2'b10, 2'b10)); // A=10, B=10, S=11
    test_add(2'b10, 2'b11, expected_result(2'b10, 2'b11)); // A=10, B=11, S=11
    test_add(2'b11, 2'b00, expected_result(2'b11, 2'b00)); // A=11, B=00, S=11
    test_add(2'b11, 2'b01, expected_result(2'b11, 2'b01)); // A=11, B=01, S=11
    test_add(2'b11, 2'b10, expected_result(2'b11, 2'b10)); // A=11, B=10, S=11
    test_add(2'b11, 2'b11, expected_result(2'b11, 2'b11)); // A=11, B=11, S=11
    
    // Summary
    $display("\nTest Summary:");
    $display("=============");
    $display("Total tests : %0d", test_case);
    $display("Passed      : %0d", pass_count);
    $display("Failed      : %0d", fail_count);
    $display("Pass rate   : %0.2f%%", (real'(pass_count)/test_case)*100);
    
    $finish;
end

endmodule

03_verif/ADD_UNIT/tb_addunit.vcd
$version Generated by VerilatedVcd $end
$timescale 1ps $end
 $scope module TOP $end
  $scope module tb_addunit $end
   $var wire 2 # i_BM [1:0] $end
   $var wire 2 $ i_PM [1:0] $end
   $var wire 2 % o_PM [1:0] $end
   $var wire 32 & pass_count [31:0] $end
   $var wire 32 ' fail_count [31:0] $end
   $var wire 32 ( test_case [31:0] $end
   $scope module dut $end
    $var wire 2 # i_BM [1:0] $end
    $var wire 2 $ i_PM [1:0] $end
    $var wire 2 % o_PM [1:0] $end
   $upscope $end
  $upscope $end
 $upscope $end
$enddefinitions $end


#0
b00 #
b00 $
b00 %
b00000000000000000000000000000000 &
b00000000000000000000000000000000 '
b00000000000000000000000000000000 (
#10000
b01 $
b01 %
b00000000000000000000000000000001 &
b00000000000000000000000000000001 (
#20000
b10 $
b10 %
b00000000000000000000000000000010 &
b00000000000000000000000000000010 (
#30000
b11 $
b11 %
b00000000000000000000000000000011 &
b00000000000000000000000000000011 (
#40000
b01 #
b00 $
b01 %
b00000000000000000000000000000100 &
b00000000000000000000000000000100 (
#50000
b01 $
b10 %
b00000000000000000000000000000101 &
b00000000000000000000000000000101 (
#60000
b10 $
b11 %
b00000000000000000000000000000110 &
b00000000000000000000000000000110 (
#70000
b11 $
b00000000000000000000000000000111 &
b00000000000000000000000000000111 (
#80000
b10 #
b00 $
b10 %
b00000000000000000000000000001000 &
b00000000000000000000000000001000 (
#90000
b01 $
b11 %
b00000000000000000000000000001001 &
b00000000000000000000000000001001 (
#100000
b10 $
b00000000000000000000000000001010 &
b00000000000000000000000000001010 (
#110000
b11 $
b00000000000000000000000000001011 &
b00000000000000000000000000001011 (
#120000
b11 #
b00 $
b00000000000000000000000000001100 &
b00000000000000000000000000001100 (
#130000
b01 $
b00000000000000000000000000001101 &
b00000000000000000000000000001101 (
#140000
b10 $
b00000000000000000000000000001110 &
b00000000000000000000000000001110 (
#150000
b11 $
b00000000000000000000000000001111 &
b00000000000000000000000000001111 (
#160000
b00000000000000000000000000010000 &
b00000000000000000000000000010000 (
