02_rtl/Compare_unit.sv
module Compare_unit(
    input logic [1:0] i_metric_path_0,  // A
    input logic [1:0] i_metric_path_1,  // B
    output logic o_compare_less      
);

// | A  | B  | C  |
// | 00 | 00 |  1 |
// | 00 | 01 |  1 |
// | 00 | 10 |  1 |
// | 00 | 11 |  1 |
// | 01 | 00 |  0 |
// | 01 | 01 |  1 |
// | 01 | 10 |  1 |
// | 01 | 11 |  1 |
// | 10 | 00 |  0 |
// | 10 | 01 |  0 |
// | 10 | 10 |  1 |
// | 10 | 11 |  1 |
// | 11 | 00 |  0 |
// | 11 | 01 |  0 |
// | 11 | 10 |  0 |
// | 11 | 11 |  1 |

    // Correct implementation
    assign o_compare_less = (~i_metric_path_0[0] & ~i_metric_path_0[1]) |
                            ( i_metric_path_1[0] &  i_metric_path_1[1]) |
                            (~i_metric_path_0[1] &  i_metric_path_1[0]) |
                            (~i_metric_path_0[1] &  i_metric_path_1[1]) |
                            (~i_metric_path_0[0] &  i_metric_path_1[1]) ;
endmodule

02_rtl/Add_unit.sv
module Add_unit(
    input logic [1:0]       i_BM    ,
    input logic [1:0]       i_PM    ,
    output logic [1:0]      o_PM    
);

assign o_PM[0] = (!i_PM[0]&i_BM[0]) | (i_PM[0]&!i_BM[0]) | 
                 (i_PM[0]&i_BM[1]) | (i_PM[1]&i_BM[0]) | 
                 (i_PM[1]&i_BM[1]);
assign o_PM[1] = (i_PM[1] | i_BM[1]) | (i_PM[0] & i_BM[0]);

endmodule

02_rtl/ACS.sv
module ACS(
    input logic [1:0]   i_BM_0      ,
    input logic [1:0]   i_BM_1      ,

    input logic [1:0]   i_PM_0      ,
    input logic [1:0]   i_PM_1      ,

    output logic [1:0]  o_PM        
);

wire [1:0] w_metric_path_0, w_metric_path_1;
wire w_compare_less;
Add_unit ADD0(
    .i_BM    (i_BM_0),
    .i_PM    (i_PM_0),
    .o_PM    (w_metric_path_0)
);
Add_unit ADD1(
    .i_BM    (i_BM_1),
    .i_PM    (i_PM_1),
    .o_PM    (w_metric_path_1)
);

Compare_unit CP(
    .i_metric_path_0    (w_metric_path_0),  // A
    .i_metric_path_1    (w_metric_path_1),  // B
    .o_compare_less     (w_compare_less)
);

always_comb begin
    if (w_compare_less) begin
        o_PM = w_metric_path_0;
    end else begin
        o_PM = w_metric_path_1;
    end
end

endmodule

02_rtl/Add_compare_select_unit.sv
module Add_compare_select_unit(
    input logic [1:0]   i_BM_0      ,
    input logic [1:0]   i_BM_1      ,
    input logic [1:0]   i_BM_2      ,
    input logic [1:0]   i_BM_3      ,
    input logic [1:0]   i_PM_0     ,
    input logic [1:0]   i_PM_1     ,
    input logic [1:0]   i_PM_2     ,
    input logic [1:0]   i_PM_3     ,
    output logic [1:0]  o_PM_0     ,
    output logic [1:0]  o_PM_1     ,
    output logic [1:0]  o_PM_2     ,
    output logic [1:0]  o_PM_3     
);

wire [1:0] w_PM_0, w_PM_1, w_PM_2, w_PM_3;

ACS ACS_0(
    .i_BM_0      (i_BM_0),
    .i_BM_1      (i_BM_3),
    .i_PM_0      (i_PM_0),
    .i_PM_1      (i_PM_1),
    .o_PM        (w_PM_0)
);
ACS ACS_1(
    .i_BM_0      (i_BM_2),
    .i_BM_1      (i_BM_1),
    .i_PM_0      (i_PM_2),
    .i_PM_1      (i_PM_3),
    .o_PM        (w_PM_1)
);
ACS ACS_2(
    .i_BM_0      (i_BM_3),
    .i_BM_1      (i_BM_0),
    .i_PM_0      (i_PM_0),
    .i_PM_1      (i_PM_1),
    .o_PM        (w_PM_2)
);
ACS ACS_3(
    .i_BM_0      (i_BM_1),
    .i_BM_1      (i_BM_2),
    .i_PM_0      (i_PM_2),
    .i_PM_1      (i_PM_3),
    .o_PM        (w_PM_3)
);

always_comb begin
    o_PM_0 = w_PM_0;
    o_PM_1 = w_PM_1;
    o_PM_2 = w_PM_2;
    o_PM_3 = w_PM_3;
end

endmodule

03_verif/ACSU/tb_acsu.sv
`timescale 1ns/1ps
module tb_acsu();

logic [1:0] w_BM_0, w_BM_1, w_BM_2, w_BM_3;
logic [1:0] w_iPM_0, w_iPM_1, w_iPM_2, w_iPM_3;
logic [1:0] w_oPM_0, w_oPM_1, w_oPM_2, w_oPM_3;

Add_compare_select_unit ACSU(
    .i_BM_0      (w_BM_0),
    .i_BM_1      (w_BM_1),
    .i_BM_2      (w_BM_2),
    .i_BM_3      (w_BM_3),
    .i_PM_0      (w_iPM_0),
    .i_PM_1      (w_iPM_1),
    .i_PM_2      (w_iPM_2),
    .i_PM_3      (w_iPM_3),
    .o_PM_0      (w_oPM_0),
    .o_PM_1      (w_oPM_1),
    .o_PM_2      (w_oPM_2),
    .o_PM_3      (w_oPM_3)
);

initial begin
    $dumpfile("tb_acsu.vcd");
    $dumpvars(0, tb_acsu);
end

initial begin
    $display("Starting Add_compare_select_unit testbench...");
    $display("=====================================");
    
    // Initialize signals
    w_BM_0 = 2'b00;
    w_BM_1 = 2'b00;
    w_BM_2 = 2'b00;
    w_BM_3 = 2'b00;
    w_iPM_0 = 2'b00;
    w_iPM_1 = 2'b00;
    w_iPM_2 = 2'b00;
    w_iPM_3 = 2'b00;
    
    $display("Time: %0t \t|", $time);
    $display("| i_BM_0: %b \t| i_BM_1: %b \t| i_BM_2: %b \t| i_BM_3: %b \t|\n| i_PM_0: %b \t| i_PM_1: %b \t| i_PM_2: %b \t| i_PM_3: %b \t|\n| o_PM_0: %b \t| o_PM_1: %b \t| o_PM_2: %b \t| o_PM_3: %b \t|", w_BM_0, w_BM_1, w_BM_2, w_BM_3, w_iPM_0, w_iPM_1, w_iPM_2, w_iPM_3, w_oPM_0, w_oPM_1, w_oPM_2, w_oPM_3);
    
    // Test with random inputs
    for(int i = 0; i < 15; i++) begin
        #10;
        w_BM_0 = $random % 4;
        w_BM_1 = $random % 4;
        w_BM_2 = $random % 4;
        w_BM_3 = $random % 4;
        w_iPM_0 = $random % 4;
        w_iPM_1 = $random % 4;
        w_iPM_2 = $random % 4;
        w_iPM_3 = $random % 4;
        #1; // Small delay to capture outputs
        $display("Time: %0t \t|", $time);
        $display("| i_BM_0: %b \t| i_BM_1: %b \t| i_BM_2: %b \t| i_BM_3: %b \t|\n| i_PM_0: %b \t| i_PM_1: %b \t| i_PM_2: %b \t| i_PM_3: %b \t|\n| o_PM_0: %b \t| o_PM_1: %b \t| o_PM_2: %b \t| o_PM_3: %b \t|", w_BM_0, w_BM_1, w_BM_2, w_BM_3, w_iPM_0, w_iPM_1, w_iPM_2, w_iPM_3, w_oPM_0, w_oPM_1, w_oPM_2, w_oPM_3);
    end
    
    #10;
    $display("Simulation finished.");
    $display("=====================================");
    $finish;
end

endmodule

03_verif/ACSU/tb_acsu.vcd
$version Generated by VerilatedVcd $end
$timescale 1ps $end
 $scope module TOP $end
  $scope module tb_acsu $end
   $var wire 2 # w_BM_0 [1:0] $end
   $var wire 2 $ w_BM_1 [1:0] $end
   $var wire 2 % w_BM_2 [1:0] $end
   $var wire 2 & w_BM_3 [1:0] $end
   $var wire 2 ' w_iPM_0 [1:0] $end
   $var wire 2 ( w_iPM_1 [1:0] $end
   $var wire 2 ) w_iPM_2 [1:0] $end
   $var wire 2 * w_iPM_3 [1:0] $end
   $var wire 2 + w_oPM_0 [1:0] $end
   $var wire 2 , w_oPM_1 [1:0] $end
   $var wire 2 - w_oPM_2 [1:0] $end
   $var wire 2 . w_oPM_3 [1:0] $end
   $scope module ACSU $end
    $var wire 2 # i_BM_0 [1:0] $end
    $var wire 2 $ i_BM_1 [1:0] $end
    $var wire 2 % i_BM_2 [1:0] $end
    $var wire 2 & i_BM_3 [1:0] $end
    $var wire 2 ' i_PM_0 [1:0] $end
    $var wire 2 ( i_PM_1 [1:0] $end
    $var wire 2 ) i_PM_2 [1:0] $end
    $var wire 2 * i_PM_3 [1:0] $end
    $var wire 2 + o_PM_0 [1:0] $end
    $var wire 2 , o_PM_1 [1:0] $end
    $var wire 2 - o_PM_2 [1:0] $end
    $var wire 2 . o_PM_3 [1:0] $end
    $var wire 2 + w_PM_0 [1:0] $end
    $var wire 2 , w_PM_1 [1:0] $end
    $var wire 2 - w_PM_2 [1:0] $end
    $var wire 2 . w_PM_3 [1:0] $end
    $scope module ACS_0 $end
     $var wire 2 # i_BM_0 [1:0] $end
     $var wire 2 & i_BM_1 [1:0] $end
     $var wire 2 ' i_PM_0 [1:0] $end
     $var wire 2 ( i_PM_1 [1:0] $end
     $var wire 2 + o_PM [1:0] $end
     $var wire 2 / w_metric_path_0 [1:0] $end
     $var wire 2 0 w_metric_path_1 [1:0] $end
     $var wire 1 1 w_compare_less $end
     $scope module ADD0 $end
      $var wire 2 # i_BM [1:0] $end
      $var wire 2 ' i_PM [1:0] $end
      $var wire 2 / o_PM [1:0] $end
     $upscope $end
     $scope module ADD1 $end
      $var wire 2 & i_BM [1:0] $end
      $var wire 2 ( i_PM [1:0] $end
      $var wire 2 0 o_PM [1:0] $end
     $upscope $end
     $scope module CP $end
      $var wire 2 / i_metric_path_0 [1:0] $end
      $var wire 2 0 i_metric_path_1 [1:0] $end
      $var wire 1 1 o_compare_less $end
     $upscope $end
    $upscope $end
    $scope module ACS_1 $end
     $var wire 2 % i_BM_0 [1:0] $end
     $var wire 2 $ i_BM_1 [1:0] $end
     $var wire 2 ) i_PM_0 [1:0] $end
     $var wire 2 * i_PM_1 [1:0] $end
     $var wire 2 , o_PM [1:0] $end
     $var wire 2 2 w_metric_path_0 [1:0] $end
     $var wire 2 3 w_metric_path_1 [1:0] $end
     $var wire 1 4 w_compare_less $end
     $scope module ADD0 $end
      $var wire 2 % i_BM [1:0] $end
      $var wire 2 ) i_PM [1:0] $end
      $var wire 2 2 o_PM [1:0] $end
     $upscope $end
     $scope module ADD1 $end
      $var wire 2 $ i_BM [1:0] $end
      $var wire 2 * i_PM [1:0] $end
      $var wire 2 3 o_PM [1:0] $end
     $upscope $end
     $scope module CP $end
      $var wire 2 2 i_metric_path_0 [1:0] $end
      $var wire 2 3 i_metric_path_1 [1:0] $end
      $var wire 1 4 o_compare_less $end
     $upscope $end
    $upscope $end
    $scope module ACS_2 $end
     $var wire 2 & i_BM_0 [1:0] $end
     $var wire 2 # i_BM_1 [1:0] $end
     $var wire 2 ' i_PM_0 [1:0] $end
     $var wire 2 ( i_PM_1 [1:0] $end
     $var wire 2 - o_PM [1:0] $end
     $var wire 2 5 w_metric_path_0 [1:0] $end
     $var wire 2 6 w_metric_path_1 [1:0] $end
     $var wire 1 7 w_compare_less $end
     $scope module ADD0 $end
      $var wire 2 & i_BM [1:0] $end
      $var wire 2 ' i_PM [1:0] $end
      $var wire 2 5 o_PM [1:0] $end
     $upscope $end
     $scope module ADD1 $end
      $var wire 2 # i_BM [1:0] $end
      $var wire 2 ( i_PM [1:0] $end
      $var wire 2 6 o_PM [1:0] $end
     $upscope $end
     $scope module CP $end
      $var wire 2 5 i_metric_path_0 [1:0] $end
      $var wire 2 6 i_metric_path_1 [1:0] $end
      $var wire 1 7 o_compare_less $end
     $upscope $end
    $upscope $end
    $scope module ACS_3 $end
     $var wire 2 $ i_BM_0 [1:0] $end
     $var wire 2 % i_BM_1 [1:0] $end
     $var wire 2 ) i_PM_0 [1:0] $end
     $var wire 2 * i_PM_1 [1:0] $end
     $var wire 2 . o_PM [1:0] $end
     $var wire 2 8 w_metric_path_0 [1:0] $end
     $var wire 2 9 w_metric_path_1 [1:0] $end
     $var wire 1 : w_compare_less $end
     $scope module ADD0 $end
      $var wire 2 $ i_BM [1:0] $end
      $var wire 2 ) i_PM [1:0] $end
      $var wire 2 8 o_PM [1:0] $end
     $upscope $end
     $scope module ADD1 $end
      $var wire 2 % i_BM [1:0] $end
      $var wire 2 * i_PM [1:0] $end
      $var wire 2 9 o_PM [1:0] $end
     $upscope $end
     $scope module CP $end
      $var wire 2 8 i_metric_path_0 [1:0] $end
      $var wire 2 9 i_metric_path_1 [1:0] $end
      $var wire 1 : o_compare_less $end
     $upscope $end
    $upscope $end
   $upscope $end
   $scope module unnamedblk1 $end
    $var wire 32 ; i [31:0] $end
   $upscope $end
  $upscope $end
 $upscope $end
$enddefinitions $end


#0
b00 #
b00 $
b00 %
b00 &
b00 '
b00 (
b00 )
b00 *
b00 +
b00 ,
b00 -
b00 .
b00 /
b00 0
11
b00 2
b00 3
14
b00 5
b00 6
17
b00 8
b00 9
1:
b00000000000000000000000000000000 ;
#10000
b10 %
b10 )
b10 .
b11 2
04
b10 8
b10 9
#11000
b00000000000000000000000000000001 ;
#21000
b11 #
b11 $
b01 %
b01 &
b01 '
b10 (
b01 *
b11 +
b11 ,
b10 -
b11 /
b11 0
b11 3
14
b10 5
b11 6
b11 8
0:
#22000
b00000000000000000000000000000010 ;
#32000
b10 #
b10 $
b00 &
b11 '
b00 (
b00 *
b00 +
b10 ,
b01 .
b00 0
01
b10 3
04
b11 5
b10 6
07
b01 9
#33000
b00000000000000000000000000000011 ;
#43000
b10 %
b10 &
b00 '
b10 (
b11 )
b10 +
b10 .
b10 /
b11 0
11
b10 5
b11 6
17
b10 9
#44000
b00000000000000000000000000000100 ;
#54000
b01 #
b01 &
b11 '
b00 (
b10 *
b01 +
b11 ,
b01 -
b11 .
b11 /
b01 0
01
b11 3
14
b11 5
b01 6
07
b11 9
1:
#55000
b00000000000000000000000000000101 ;
#65000
b11 #
b01 $
b11 &
b10 '
b11 *
b11 +
b11 -
b11 0
11
b11 6
17
#66000
b00000000000000000000000000000110 ;
#76000
b00 #
b10 $
b01 '
b11 (
b00 *
b01 +
b10 ,
b10 .
b01 /
b10 3
04
b10 9
0:
#77000
b00000000000000000000000000000111 ;
#87000
b01 #
b11 $
b11 %
b00 &
b11 '
b01 (
b01 )
b10 *
b11 ,
b10 -
b11 .
b11 /
b01 0
01
b11 3
14
b10 6
07
b11 9
1:
#88000
b00000000000000000000000000001000 ;
#98000
b00 %
b11 &
b01 '
b00 *
b10 +
b01 ,
b00 .
b10 /
b11 0
11
b01 2
b00 9
0:
#99000
b00000000000000000000000000001001 ;
#109000
b10 #
b10 $
b00 &
b11 '
b11 )
b01 *
b01 +
b11 ,
b11 -
b01 .
b11 /
b01 0
01
b11 2
b11 6
17
b01 9
#110000
b00000000000000000000000000001010 ;
#120000
b01 #
b11 %
b01 &
b10 )
b11 *
b10 +
b10 -
b11 .
b10 0
b10 6
07
b11 9
1:
#121000
b00000000000000000000000000001011 ;
#131000
b11 #
b01 $
b11 &
b10 '
b11 (
b11 +
b11 -
b11 0
11
b11 6
17
#132000
b00000000000000000000000000001100 ;
#142000
b11 $
b00 %
b10 &
b11 '
b00 (
b01 *
b10 +
b10 ,
b01 .
b10 0
01
b10 2
b01 9
0:
#143000
b00000000000000000000000000001101 ;
#153000
b00 #
b00 $
b01 %
b01 &
b01 '
b11 (
b01 )
b01 +
b01 ,
b10 -
b01 /
b11 0
11
b01 3
04
b10 5
b01 8
b10 9
1:
#154000
b00000000000000000000000000001110 ;
#164000
b01 #
b10 $
b10 %
b10 &
b00 '
b01 (
b00 )
b00 *
b10 ,
b10 .
b10 3
14
b10 6
b10 8
#165000
b00000000000000000000000000001111 ;
