02_rtl/Compare_unit.sv
module Compare_unit(
    input logic [1:0] i_metric_path_0,  // A
    input logic [1:0] i_metric_path_1,  // B
    output logic o_compare_less      
);

// | A  | B  | C  |
// | 00 | 00 |  1 |
// | 00 | 01 |  1 |
// | 00 | 10 |  1 |
// | 00 | 11 |  1 |
// | 01 | 00 |  0 |
// | 01 | 01 |  1 |
// | 01 | 10 |  1 |
// | 01 | 11 |  1 |
// | 10 | 00 |  0 |
// | 10 | 01 |  0 |
// | 10 | 10 |  1 |
// | 10 | 11 |  1 |
// | 11 | 00 |  0 |
// | 11 | 01 |  0 |
// | 11 | 10 |  0 |
// | 11 | 11 |  1 |

    // Correct implementation
    assign o_compare_less = (~i_metric_path_0[0] & ~i_metric_path_0[1]) |
                            ( i_metric_path_1[0] &  i_metric_path_1[1]) |
                            (~i_metric_path_0[1] &  i_metric_path_1[0]) |
                            (~i_metric_path_0[1] &  i_metric_path_1[1]) |
                            (~i_metric_path_0[0] &  i_metric_path_1[1]) ;
endmodule

02_rtl/Add_unit.sv
module Add_unit(
    input logic [1:0]       i_BM    ,
    input logic [1:0]       i_PM    ,
    output logic [1:0]      o_PM    
);

assign o_PM[0] = (!i_PM[0]&i_BM[0]) | (i_PM[0]&!i_BM[0]) | 
                 (i_PM[0]&i_BM[1]) | (i_PM[1]&i_BM[0]) | 
                 (i_PM[1]&i_BM[1]);
assign o_PM[1] = (i_PM[1] | i_BM[1]) | (i_PM[0] & i_BM[0]);

endmodule

02_rtl/Add_compare_select_unit.sv
module Add_compare_select_unit(
    input logic [1:0]   i_BM_0      ,
    input logic [1:0]   i_BM_1      ,
    input logic [1:0]   i_BM_2      ,
    input logic [1:0]   i_BM_3      ,
    input logic [1:0]   i_PM_0     ,
    input logic [1:0]   i_PM_1     ,
    input logic [1:0]   i_PM_2     ,
    input logic [1:0]   i_PM_3     ,
    output logic [1:0]  o_PM_0     ,
    output logic [1:0]  o_PM_1     ,
    output logic [1:0]  o_PM_2     ,
    output logic [1:0]  o_PM_3     
);

wire [1:0] w_PM_0, w_PM_1, w_PM_2, w_PM_3;

ACS ACS_0(
    .i_BM_0      (i_BM_0),
    .i_BM_1      (i_BM_3),
    .i_PM_0      (i_PM_0),
    .i_PM_1      (i_PM_1),
    .o_PM        (w_PM_0)
);
ACS ACS_1(
    .i_BM_0      (i_BM_2),
    .i_BM_1      (i_BM_1),
    .i_PM_0      (i_PM_2),
    .i_PM_1      (i_PM_3),
    .o_PM        (w_PM_1)
);
ACS ACS_2(
    .i_BM_0      (i_BM_3),
    .i_BM_1      (i_BM_0),
    .i_PM_0      (i_PM_0),
    .i_PM_1      (i_PM_1),
    .o_PM        (w_PM_2)
);
ACS ACS_3(
    .i_BM_0      (i_BM_1),
    .i_BM_1      (i_BM_2),
    .i_PM_0      (i_PM_2),
    .i_PM_1      (i_PM_3),
    .o_PM        (w_PM_3)
);

always_comb begin
    o_PM_0 = w_PM_0;
    o_PM_1 = w_PM_1;
    o_PM_2 = w_PM_2;
    o_PM_3 = w_PM_3;
end

endmodule

module ACS(
    input logic [1:0]   i_BM_0      ,
    input logic [1:0]   i_BM_1      ,

    input logic [1:0]   i_PM_0      ,
    input logic [1:0]   i_PM_1      ,

    output logic [1:0]  o_PM        
);

wire [1:0] w_metric_path_0, w_metric_path_1;
wire w_compare_less;
Add_unit ADD0(
    .i_BM    (i_BM_0),
    .i_PM    (i_PM_0),
    .o_PM    (w_metric_path_0)
);
Add_unit ADD1(
    .i_BM    (i_BM_1),
    .i_PM    (i_PM_1),
    .o_PM    (w_metric_path_1)
);

Compare_unit CP(
    .i_metric_path_0    (w_metric_path_0),  // A
    .i_metric_path_1    (w_metric_path_1),  // B
    .o_compare_less     (w_compare_less)
);

always_comb begin
    if (w_compare_less) begin
        o_PM = w_metric_path_0;
    end else begin
        o_PM = w_metric_path_1;
    end
end

endmodule

02_rtl/D_BMU_ACSU.sv
module D_BMU_ACSU(
    input logic             i_clk       ,
    input logic             i_rst_n     ,
    input logic             i_valid     ,
    input logic [1:0]   i_BM_0      ,
    input logic [1:0]   i_BM_1      ,
    input logic [1:0]   i_BM_2      ,
    input logic [1:0]   i_BM_3      ,
    input logic [1:0]   i_PM_0     ,
    input logic [1:0]   i_PM_1     ,
    input logic [1:0]   i_PM_2     ,
    input logic [1:0]   i_PM_3     ,
    output logic [1:0]   o_BM_0      ,
    output logic [1:0]   o_BM_1      ,
    output logic [1:0]   o_BM_2      ,
    output logic [1:0]   o_BM_3      ,
    output logic [1:0]   o_PM_0     ,
    output logic [1:0]   o_PM_1     ,
    output logic [1:0]   o_PM_2     ,
    output logic [1:0]   o_PM_3     ,
    output logic         o_valid    
);

always_ff @(posedge i_clk or negedge i_rst_n) begin
    if(~i_rst_n) begin 
       o_BM_0       <=  0;     
       o_BM_1       <=  0;
       o_BM_2       <=  0;
       o_BM_3       <=  0;
       o_PM_0       <=  2'b00;
       o_PM_1       <=  2'b11;
       o_PM_2       <=  2'b11;
       o_PM_3       <=  2'b11;
       o_valid      <=  0;
   end else if(i_valid) begin
        o_BM_0       <=  i_BM_0;     
        o_BM_1       <=  i_BM_1;
        o_BM_2       <=  i_BM_2;
        o_BM_3       <=  i_BM_3;
        o_PM_0       <=  i_PM_0;
        o_PM_1       <=  i_PM_1;
        o_PM_2       <=  i_PM_2;
        o_PM_3       <=  i_PM_3;
        o_valid      <=  1;
   end else begin
        o_BM_0       <=  o_BM_0;     
        o_BM_1       <=  o_BM_1;
        o_BM_2       <=  o_BM_2;
        o_BM_3       <=  o_BM_3;
        o_PM_0       <=  o_PM_0;
        o_PM_1       <=  o_PM_1;
        o_PM_2       <=  o_PM_2;
        o_PM_3       <=  o_PM_3;
        o_valid      <=  0;
   end 
end 

endmodule

03_verif/ACSU/tb_acsu.sv
// `timescale 1ns/1ps
// module tb_acsu();

// logic [1:0] w_BM_0, w_BM_1, w_BM_2, w_BM_3;
// logic [1:0] w_iPM_0, w_iPM_1, w_iPM_2, w_iPM_3;
// logic [1:0] w_oPM_0, w_oPM_1, w_oPM_2, w_oPM_3
// logic [1:0] t_oPM_0, t_oPM_1, t_oPM_2, t_oPM_3;

// Add_compare_select_unit ACSU(
//     .i_BM_0      (w_BM_0),
//     .i_BM_1      (w_BM_1),
//     .i_BM_2      (w_BM_2),
//     .i_BM_3      (w_BM_3),
//     .i_PM_0      (w_iPM_0),
//     .i_PM_1      (w_iPM_1),
//     .i_PM_2      (w_iPM_2),
//     .i_PM_3      (w_iPM_3),
//     .o_PM_0      (w_oPM_0),
//     .o_PM_1      (w_oPM_1),
//     .o_PM_2      (w_oPM_2),
//     .o_PM_3      (w_oPM_3)
// );

// initial begin
//     $dumpfile("tb_acsu.vcd");
//     $dumpvars(0, tb_acsu);
// end

// // task CheckResult(
// //     input logic [1:0] i_BM_0, input logic [1:0] i_BM_1,
// //     input logic [1:0] i_BM_2, input logic [1:0] i_BM_3,
// //     input logic [1:0] i_PM_0, input logic [1:0] i_PM_1,
// //     input logic [1:0] i_PM_2, input logic [1:0] i_PM_3,
// //     output logic [1:0] o_PM_0, output logic [1:0] o_PM_1,
// //     output logic [1:0] o_PM_2, output logic [1:0] o_PM_3
// // );
// //     logic [1:0] w_oPM_0, w_oPM_1, w_oPM_2, w_oPM_3;
// //     // Check the outputs based on the inputs
// //     t_oPM_0 = (i_BM_0 + i_PM_0) <= (i_BM_3 + i_PM_1) ? (i_BM_0 + i_PM_0) : (i_BM_3 + i_PM_1);
// //     t_oPM_1 = (i_BM_2 + i_PM_2) <= (i_BM_1 + i_PM_3) ? (i_BM_2 + i_PM_2) : (i_BM_1 + i_PM_3);
// //     t_oPM_2 = (i_BM_3 + i_PM_0) <= (i_BM_0 + i_PM_1) ? (i_BM_3 + i_PM_0) : (i_BM_0 + i_PM_1);
// //     t_oPM_3 = (i_BM_1 + i_PM_2) <= (i_BM_2 + i_PM_3) ? (i_BM_1 + i_PM_2) : (i_BM_2 + i_PM_3);
// //     $display("-> %s", (w_oPM_0 == o_PM_0 && w_oPM_1 == o_PM_1 && w_oPM_2 == o_PM_2 && w_oPM_3 == o_PM_3) ? "PASS" : "FAIL");
// // endtask //automatic

// initial begin
//     $display("Starting Add_compare_select_unit testbench...");
//     $display("=====================================");
    
//     // Initialize signals
//     w_BM_0 = 2'b00;
//     w_BM_1 = 2'b00;
//     w_BM_2 = 2'b00;
//     w_BM_3 = 2'b00;
//     w_iPM_0 = 2'b00;
//     w_iPM_1 = 2'b00;
//     w_iPM_2 = 2'b00;
//     w_iPM_3 = 2'b00;
    
//     $display("Time: %0t \t|", $time);
//     $display("| i_BM_0: %b \t| i_BM_1: %b \t| i_BM_2: %b \t| i_BM_3: %b \t|\n| i_PM_0: %b \t| i_PM_1: %b \t| i_PM_2: %b \t| i_PM_3: %b \t|\n| o_PM_0: %b \t| o_PM_1: %b \t| o_PM_2: %b \t| o_PM_3: %b \t|", w_BM_0, w_BM_1, w_BM_2, w_BM_3, w_iPM_0, w_iPM_1, w_iPM_2, w_iPM_3, w_oPM_0, w_oPM_1, w_oPM_2, w_oPM_3);
    
//     // Test with random inputs
//     for(int i = 0; i < 15; i++) begin
//         #10;
//         w_BM_0 = $random % 4;
//         w_BM_1 = $random % 4;
//         w_BM_2 = $random % 4;
//         w_BM_3 = $random % 4;
//         w_iPM_0 = $random % 4;
//         w_iPM_1 = $random % 4;
//         w_iPM_2 = $random % 4;
//         w_iPM_3 = $random % 4;
//         t_oPM_0 = (i_BM_0 + i_PM_0) <= (i_BM_3 + i_PM_1) ? (i_BM_0 + i_PM_0) : (i_BM_3 + i_PM_1);
//         t_oPM_1 = (i_BM_2 + i_PM_2) <= (i_BM_1 + i_PM_3) ? (i_BM_2 + i_PM_2) : (i_BM_1 + i_PM_3);
//         t_oPM_2 = (i_BM_3 + i_PM_0) <= (i_BM_0 + i_PM_1) ? (i_BM_3 + i_PM_0) : (i_BM_0 + i_PM_1);
//         t_oPM_3 = (i_BM_1 + i_PM_2) <= (i_BM_2 + i_PM_3) ? (i_BM_1 + i_PM_2) : (i_BM_2 + i_PM_3);
//         #1; // Small delay to capture outputs
//         $display("Time: %0t \t|", $time);
//         $display("| i_BM_0: %b \t| i_BM_1: %b \t| i_BM_2: %b \t| i_BM_3: %b \t|\n| i_PM_0: %b \t| i_PM_1: %b \t| i_PM_2: %b \t| i_PM_3: %b \t|\n| o_PM_0: %b \t| o_PM_1: %b \t| o_PM_2: %b \t| o_PM_3: %b \t|", w_BM_0, w_BM_1, w_BM_2, w_BM_3, w_iPM_0, w_iPM_1, w_iPM_2, w_iPM_3, w_oPM_0, w_oPM_1, w_oPM_2, w_oPM_3);
//         $display("-> %s", (w_oPM_0 == t_oPM_0 && w_oPM_1 == t_oPM_1 && w_oPM_2 == t_oPM_2 && w_oPM_3 == t_oPM_3) ? "PASS" : "FAIL");
//         $display("=====================================");
//     end
    
//     #10;
//     $display("Simulation finished.");
//     $display("=====================================");
//     $finish;
// end

// endmodule

`timescale 1ns/1ps
module tb_acsu();

logic w_clk, w_rst_n, i_valid, o_valid;
logic [1:0] i_BM_0, i_BM_1, i_BM_2, i_BM_3;
logic [1:0] o_BM_0, o_BM_1, o_BM_2, o_BM_3;
logic [1:0] i_PM_0, i_PM_1, i_PM_2, i_PM_3;
logic [1:0] o_PM_0, o_PM_1, o_PM_2, o_PM_3;

D_BMU_ACSU DFF(
    .i_clk        (w_clk),
    .i_rst_n      (w_rst_n),
    .i_valid      (i_valid),
    .i_BM_0       (i_BM_0),
    .i_BM_1       (i_BM_1),
    .i_BM_2       (i_BM_2),
    .i_BM_3       (i_BM_3),
    .i_PM_0       (o_PM_0),
    .i_PM_1       (o_PM_1),
    .i_PM_2       (o_PM_2),
    .i_PM_3       (o_PM_3),
    .o_BM_0       (o_BM_0),
    .o_BM_1       (o_BM_1),
    .o_BM_2       (o_BM_2),
    .o_BM_3       (o_BM_3),
    .o_PM_0       (i_PM_0),
    .o_PM_1       (i_PM_1),
    .o_PM_2       (i_PM_2),
    .o_PM_3       (i_PM_3),
    .o_valid      (o_valid)
);

Add_compare_select_unit ACSU(
    .i_BM_0      (o_BM_0),
    .i_BM_1      (o_BM_1),
    .i_BM_2      (o_BM_2),
    .i_BM_3      (o_BM_3),
    .i_PM_0      (i_PM_0),
    .i_PM_1      (i_PM_1),
    .i_PM_2      (i_PM_2),
    .i_PM_3      (i_PM_3),
    .o_PM_0      (o_PM_0),
    .o_PM_1      (o_PM_1),
    .o_PM_2      (o_PM_2),
    .o_PM_3      (o_PM_3)
);

initial begin
    $dumpfile("tb_acsu.vcd");
    $dumpvars(0, tb_acsu);
end

// Clock generation
always begin
    #5 w_clk = ~w_clk; // Toggle clock every 5 time units
end
task automatic CheckResult(
    input logic [1:0] t_i_BM_0, t_i_BM_1, t_i_BM_2, t_i_BM_3,
    input logic [1:0] t_i_PM_0, t_i_PM_1, t_i_PM_2, t_i_PM_3,
    input logic [1:0] t_o_PM_0, t_o_PM_1, t_o_PM_2, t_o_PM_3
);
    logic [1:0] t_oPM_0, t_oPM_1, t_oPM_2, t_oPM_3;
    // Calculate expected outputs
    t_oPM_0 = (t_i_BM_0 + t_i_PM_0) <= (t_i_BM_3 + t_i_PM_1) ? (t_i_BM_0 + t_i_PM_0) : (t_i_BM_3 + t_i_PM_1);
    t_oPM_1 = (t_i_BM_2 + t_i_PM_2) <= (t_i_BM_1 + t_i_PM_3) ? (t_i_BM_2 + t_i_PM_2) : (t_i_BM_1 + t_i_PM_3);
    t_oPM_2 = (t_i_BM_3 + t_i_PM_0) <= (t_i_BM_0 + t_i_PM_1) ? (t_i_BM_3 + t_i_PM_0) : (t_i_BM_0 + t_i_PM_1);
    t_oPM_3 = (t_i_BM_1 + t_i_PM_2) <= (t_i_BM_2 + t_i_PM_3) ? (t_i_BM_1 + t_i_PM_2) : (t_i_BM_2 + t_i_PM_3);
    
    @(posedge w_clk); // Wait for clock edge to capture outputs
    $display("Time: %0t", $time);
    $display("| i_BM_0: %b | i_BM_1: %b | i_BM_2: %b | i_BM_3: %b |", 
             t_i_BM_0, t_i_BM_1, t_i_BM_2, t_i_BM_3);
    $display("| i_PM_0: %b | i_PM_1: %b | i_PM_2: %b | i_PM_3: %b |", 
             t_i_PM_0, t_i_PM_1, t_i_PM_2, t_i_PM_3);
    #1; // Small delay to ensure outputs are stable
    $display("| o_PM_0: %b | o_PM_1: %b | o_PM_2: %b | o_PM_3: %b |", 
             t_o_PM_0, t_o_PM_1, t_o_PM_2, t_o_PM_3);
    $display("| t_oPM_0: %b | t_oPM_1: %b | t_oPM_2: %b | t_oPM_3: %b |", 
             t_oPM_0, t_oPM_1, t_oPM_2, t_oPM_3);
    $display("-> %s", (t_o_PM_0 == t_oPM_0 && t_o_PM_1 == t_oPM_1 && 
                      t_o_PM_2 == t_oPM_2 && t_o_PM_3 == t_oPM_3) ? "PASS" : "FAIL");
    $display("=====================================");
endtask

initial begin
    w_rst_n = 0;
    i_valid = 0;
    #10; // Hold reset for 10 time units
    $display("Starting Add_compare_select_unit testbench...");
    w_rst_n = 1; // Release reset
    i_valid = 1; // Set valid signal to indicate inputs are ready
    i_BM_0 = 2'b00; i_BM_1 = 2'b00; i_BM_2 = 2'b00; i_BM_3 = 2'b00;
    $display("TestCase 0: Initialize signals");
    CheckResult(i_BM_0, i_BM_1, i_BM_2, i_BM_3, i_PM_0, i_PM_1, i_PM_2, i_PM_3, 
    o_PM_0, o_PM_1, o_PM_2, o_PM_3);
    #20;
    CheckResult(i_BM_0, i_BM_1, i_BM_2, i_BM_3, i_PM_0, i_PM_1, i_PM_2, i_PM_3, 
    o_PM_0, o_PM_1, o_PM_2, o_PM_3);
    $display("=====================================");
    
    // Test case 1: All inputs are equal
    @(posedge w_clk);
    $display("TestCase 1: All inputs are equal");
    i_BM_0 = 2'b01; i_BM_1 = 2'b01; i_BM_2 = 2'b01; i_BM_3 = 2'b01;
    CheckResult(i_BM_0, i_BM_1, i_BM_2, i_BM_3, i_PM_0, i_PM_1, i_PM_2, i_PM_3, 
                o_PM_0, o_PM_1, o_PM_2, o_PM_3);
    
    // Test case 2: Different values
    @(posedge w_clk);
    $display("TestCase 2: Different values");
    i_BM_0 = 2'b00; i_BM_1 = 2'b01; i_BM_2 = 2'b10; i_BM_3 = 2'b11;
    CheckResult(i_BM_0, i_BM_1, i_BM_2, i_BM_3, i_PM_0, i_PM_1, i_PM_2, i_PM_3, 
                o_PM_0, o_PM_1, o_PM_2, o_PM_3);
    
    // Random test cases
    $display("TestCase 3: Random test cases");
    for(int i = 0; i < 5; i++) begin
        @(posedge w_clk);
        i_BM_0 = $urandom % 4;
        i_BM_1 = $urandom % 4;
        i_BM_2 = $urandom % 4;
        i_BM_3 = $urandom % 4;
        CheckResult(i_BM_0, i_BM_1, i_BM_2, i_BM_3, i_PM_0, i_PM_1, i_PM_2, i_PM_3, 
                o_PM_0, o_PM_1, o_PM_2, o_PM_3);
    end
    
    #20;
    $display("Simulation finished.");
    $display("=====================================");
    $finish;
end

endmodule

03_verif/ACSU/tb_acsu.vcd
$version Generated by VerilatedVcd $end
$timescale 1ps $end
 $scope module TOP $end
  $scope module tb_acsu $end
   $var wire 1 C w_clk $end
   $var wire 1 # w_rst_n $end
   $var wire 1 $ i_valid $end
   $var wire 1 * o_valid $end
   $var wire 2 % i_BM_0 [1:0] $end
   $var wire 2 & i_BM_1 [1:0] $end
   $var wire 2 ' i_BM_2 [1:0] $end
   $var wire 2 ( i_BM_3 [1:0] $end
   $var wire 2 + o_BM_0 [1:0] $end
   $var wire 2 , o_BM_1 [1:0] $end
   $var wire 2 - o_BM_2 [1:0] $end
   $var wire 2 . o_BM_3 [1:0] $end
   $var wire 2 / i_PM_0 [1:0] $end
   $var wire 2 0 i_PM_1 [1:0] $end
   $var wire 2 1 i_PM_2 [1:0] $end
   $var wire 2 2 i_PM_3 [1:0] $end
   $var wire 2 3 o_PM_0 [1:0] $end
   $var wire 2 4 o_PM_1 [1:0] $end
   $var wire 2 5 o_PM_2 [1:0] $end
   $var wire 2 6 o_PM_3 [1:0] $end
   $scope module ACSU $end
    $var wire 2 + i_BM_0 [1:0] $end
    $var wire 2 , i_BM_1 [1:0] $end
    $var wire 2 - i_BM_2 [1:0] $end
    $var wire 2 . i_BM_3 [1:0] $end
    $var wire 2 / i_PM_0 [1:0] $end
    $var wire 2 0 i_PM_1 [1:0] $end
    $var wire 2 1 i_PM_2 [1:0] $end
    $var wire 2 2 i_PM_3 [1:0] $end
    $var wire 2 3 o_PM_0 [1:0] $end
    $var wire 2 4 o_PM_1 [1:0] $end
    $var wire 2 5 o_PM_2 [1:0] $end
    $var wire 2 6 o_PM_3 [1:0] $end
    $var wire 2 3 w_PM_0 [1:0] $end
    $var wire 2 4 w_PM_1 [1:0] $end
    $var wire 2 5 w_PM_2 [1:0] $end
    $var wire 2 6 w_PM_3 [1:0] $end
    $scope module ACS_0 $end
     $var wire 2 + i_BM_0 [1:0] $end
     $var wire 2 . i_BM_1 [1:0] $end
     $var wire 2 / i_PM_0 [1:0] $end
     $var wire 2 0 i_PM_1 [1:0] $end
     $var wire 2 3 o_PM [1:0] $end
     $var wire 2 7 w_metric_path_0 [1:0] $end
     $var wire 2 8 w_metric_path_1 [1:0] $end
     $var wire 1 9 w_compare_less $end
     $scope module ADD0 $end
      $var wire 2 + i_BM [1:0] $end
      $var wire 2 / i_PM [1:0] $end
      $var wire 2 7 o_PM [1:0] $end
     $upscope $end
     $scope module ADD1 $end
      $var wire 2 . i_BM [1:0] $end
      $var wire 2 0 i_PM [1:0] $end
      $var wire 2 8 o_PM [1:0] $end
     $upscope $end
     $scope module CP $end
      $var wire 2 7 i_metric_path_0 [1:0] $end
      $var wire 2 8 i_metric_path_1 [1:0] $end
      $var wire 1 9 o_compare_less $end
     $upscope $end
    $upscope $end
    $scope module ACS_1 $end
     $var wire 2 - i_BM_0 [1:0] $end
     $var wire 2 , i_BM_1 [1:0] $end
     $var wire 2 1 i_PM_0 [1:0] $end
     $var wire 2 2 i_PM_1 [1:0] $end
     $var wire 2 4 o_PM [1:0] $end
     $var wire 2 : w_metric_path_0 [1:0] $end
     $var wire 2 ; w_metric_path_1 [1:0] $end
     $var wire 1 < w_compare_less $end
     $scope module ADD0 $end
      $var wire 2 - i_BM [1:0] $end
      $var wire 2 1 i_PM [1:0] $end
      $var wire 2 : o_PM [1:0] $end
     $upscope $end
     $scope module ADD1 $end
      $var wire 2 , i_BM [1:0] $end
      $var wire 2 2 i_PM [1:0] $end
      $var wire 2 ; o_PM [1:0] $end
     $upscope $end
     $scope module CP $end
      $var wire 2 : i_metric_path_0 [1:0] $end
      $var wire 2 ; i_metric_path_1 [1:0] $end
      $var wire 1 < o_compare_less $end
     $upscope $end
    $upscope $end
    $scope module ACS_2 $end
     $var wire 2 . i_BM_0 [1:0] $end
     $var wire 2 + i_BM_1 [1:0] $end
     $var wire 2 / i_PM_0 [1:0] $end
     $var wire 2 0 i_PM_1 [1:0] $end
     $var wire 2 5 o_PM [1:0] $end
     $var wire 2 = w_metric_path_0 [1:0] $end
     $var wire 2 > w_metric_path_1 [1:0] $end
     $var wire 1 ? w_compare_less $end
     $scope module ADD0 $end
      $var wire 2 . i_BM [1:0] $end
      $var wire 2 / i_PM [1:0] $end
      $var wire 2 = o_PM [1:0] $end
     $upscope $end
     $scope module ADD1 $end
      $var wire 2 + i_BM [1:0] $end
      $var wire 2 0 i_PM [1:0] $end
      $var wire 2 > o_PM [1:0] $end
     $upscope $end
     $scope module CP $end
      $var wire 2 = i_metric_path_0 [1:0] $end
      $var wire 2 > i_metric_path_1 [1:0] $end
      $var wire 1 ? o_compare_less $end
     $upscope $end
    $upscope $end
    $scope module ACS_3 $end
     $var wire 2 , i_BM_0 [1:0] $end
     $var wire 2 - i_BM_1 [1:0] $end
     $var wire 2 1 i_PM_0 [1:0] $end
     $var wire 2 2 i_PM_1 [1:0] $end
     $var wire 2 6 o_PM [1:0] $end
     $var wire 2 @ w_metric_path_0 [1:0] $end
     $var wire 2 A w_metric_path_1 [1:0] $end
     $var wire 1 B w_compare_less $end
     $scope module ADD0 $end
      $var wire 2 , i_BM [1:0] $end
      $var wire 2 1 i_PM [1:0] $end
      $var wire 2 @ o_PM [1:0] $end
     $upscope $end
     $scope module ADD1 $end
      $var wire 2 - i_BM [1:0] $end
      $var wire 2 2 i_PM [1:0] $end
      $var wire 2 A o_PM [1:0] $end
     $upscope $end
     $scope module CP $end
      $var wire 2 @ i_metric_path_0 [1:0] $end
      $var wire 2 A i_metric_path_1 [1:0] $end
      $var wire 1 B o_compare_less $end
     $upscope $end
    $upscope $end
   $upscope $end
   $scope module DFF $end
    $var wire 1 C i_clk $end
    $var wire 1 # i_rst_n $end
    $var wire 1 $ i_valid $end
    $var wire 2 % i_BM_0 [1:0] $end
    $var wire 2 & i_BM_1 [1:0] $end
    $var wire 2 ' i_BM_2 [1:0] $end
    $var wire 2 ( i_BM_3 [1:0] $end
    $var wire 2 3 i_PM_0 [1:0] $end
    $var wire 2 4 i_PM_1 [1:0] $end
    $var wire 2 5 i_PM_2 [1:0] $end
    $var wire 2 6 i_PM_3 [1:0] $end
    $var wire 2 + o_BM_0 [1:0] $end
    $var wire 2 , o_BM_1 [1:0] $end
    $var wire 2 - o_BM_2 [1:0] $end
    $var wire 2 . o_BM_3 [1:0] $end
    $var wire 2 / o_PM_0 [1:0] $end
    $var wire 2 0 o_PM_1 [1:0] $end
    $var wire 2 1 o_PM_2 [1:0] $end
    $var wire 2 2 o_PM_3 [1:0] $end
    $var wire 1 * o_valid $end
   $upscope $end
   $scope module unnamedblk1 $end
    $var wire 32 ) i [31:0] $end
   $upscope $end
  $upscope $end
 $upscope $end
$enddefinitions $end


#0
0#
0$
b00 %
b00 &
b00 '
b00 (
b00000000000000000000000000000000 )
0*
b00 +
b00 ,
b00 -
b00 .
b00 /
b00 0
b00 1
b00 2
b00 3
b00 4
b00 5
b00 6
b00 7
b00 8
19
b00 :
b00 ;
1<
b00 =
b00 >
1?
b00 @
b00 A
1B
0C
#5000
b11 0
b11 1
b11 2
b11 4
b11 6
b11 8
b11 :
b11 ;
b11 >
b11 @
b11 A
1C
#10000
1#
1$
0C
#15000
1*
b00 1
b00 4
b00 6
b00 :
b00 @
1C
#16000
#20000
0C
#25000
b00 0
b00 2
b00 8
b00 ;
b00 >
b00 A
1C
#30000
0C
#35000
1C
#36000
#40000
0C
#45000
1C
#46000
#50000
0C
#55000
b01 %
b01 &
b01 '
b01 (
b01 +
b01 ,
b01 -
b01 .
b01 3
b01 4
b01 5
b01 6
b01 7
b01 8
b01 :
b01 ;
b01 =
b01 >
b01 @
b01 A
1C
#60000
0C
#65000
b01 /
b01 0
b01 1
b01 2
b10 3
b10 4
b10 5
b10 6
b10 7
b10 8
b10 :
b10 ;
b10 =
b10 >
b10 @
b10 A
1C
#66000
#70000
0C
#75000
b00 %
b10 '
b11 (
b00 +
b10 -
b11 .
b10 /
b10 0
b10 1
b10 2
b11 4
b11 6
b11 8
b11 :
b11 ;
b11 =
0?
b11 @
b11 A
1C
#80000
0C
#85000
b11 0
b11 2
b11 5
b11 >
1?
1C
#86000
#90000
0C
#95000
b00 &
b00 (
b00 ,
b00 .
b11 1
b10 5
b10 =
1C
#100000
0C
#105000
b10 1
b10 6
b10 @
1C
#106000
b00000000000000000000000000000001 )
#110000
0C
#115000
b10 2
b10 4
b10 ;
0<
1C
#120000
0C
#125000
b10 0
b10 8
b10 >
1C
#126000
b00000000000000000000000000000010 )
#130000
0C
#135000
b11 %
b11 &
b01 '
b01 (
b11 +
b11 ,
b01 -
b01 .
b11 3
b11 4
b11 5
b11 6
b11 7
b11 8
b11 ;
1<
b11 =
b11 >
b11 @
1C
#140000
0C
#145000
b11 /
b11 0
b11 1
b11 2
1C
#146000
b00000000000000000000000000000011 )
#150000
0C
#155000
b01 %
b10 &
b10 '
b01 +
b10 ,
b10 -
1C
#160000
0C
#165000
1C
#166000
b00000000000000000000000000000100 )
#170000
0C
#175000
b10 %
b01 '
b00 (
b10 +
b01 -
b00 .
1C
#180000
0C
#185000
1C
#186000
b00000000000000000000000000000101 )
