02_rtl/Survivor_path_memory_unit.sv
module Survivor_path_memory_unit(
    input logic         i_clk       ,
    input logic         i_rst_n     ,

    input logic         i_valid     ,
    input logic [1:0]   i_PM_0      ,
    input logic [1:0]   i_PM_1      ,
    input logic [1:0]   i_PM_2      ,
    input logic [1:0]   i_PM_3      ,

    output logic        o_decision
  );
  wire w_compare_0;
  wire w_compare_1;

  Compare_unit CP0(
                 .i_metric_path_0    (i_PM_0),  // A
                 .i_metric_path_1    (i_PM_2),  // B
                 .o_compare_less     (w_compare_0)
               );

  Compare_unit CP1(
                 .i_metric_path_0    (i_PM_1),  // A
                 .i_metric_path_1    (i_PM_3),  // B
                 .o_compare_less     (w_compare_1)
               );


  state_machine u_state_machine (
                  .i_clk(i_clk),
                  .i_rst_n(i_rst_n),
                  .i_valid(i_valid),
                  .i_compare_0(w_compare_0),
                  .i_compare_1(w_compare_1),
                  .o_decision(o_decision)
                );

endmodule

module state_machine(
    input logic         i_clk,
    input logic         i_rst_n,
    input logic         i_valid,
    input logic         i_compare_0,
    input logic         i_compare_1,
    output logic        o_decision
  );

  parameter logic [1:0] S0 = 2'b00;
  parameter logic [1:0] S1 = 2'b01;
  parameter logic [1:0] S2 = 2'b10;
  parameter logic [1:0] S3 = 2'b11;

  logic [1:0] state, nstate;

  next_state_logic NSL(
                     .i_valid          (i_valid),
                     .i_compare_0      (i_compare_0),
                     .i_compare_1      (i_compare_1),
                     .i_pre_state      (state),
                     .o_next_state     (nstate)
                   );

  state_memory SM(
                 .i_clk            (i_clk),
                 .i_rst_n          (i_rst_n),
                 .i_next_state     (nstate),
                 .o_curr_state     (state)
               );

  output_logic OL(
                 .i_curr_state     (nstate),
                //  .i_curr_state     (state),
                 .o_decision_bit   (o_decision)
               );

endmodule

module next_state_logic(
    input logic         i_valid,
    input logic         i_compare_0,
    input logic         i_compare_1,
    input logic [1:0]   i_pre_state,
    output logic [1:0]  o_next_state
  );

  parameter logic [1:0] S0 = 2'b00;
  parameter logic [1:0] S1 = 2'b01;
  parameter logic [1:0] S2 = 2'b10;
  parameter logic [1:0] S3 = 2'b11;

  always_comb
  begin
    if (!i_valid)
    begin
      o_next_state = i_pre_state;
    end
    else
    begin
      case(i_pre_state)
        S0, S1:
        begin
          if (i_compare_0)
            o_next_state = S0;
          else
            o_next_state = S2;
        end
        S2, S3:
        begin
          if (i_compare_1)
            o_next_state = S1;
          else
            o_next_state = S3;
        end
        default:
          o_next_state = S0;
      endcase
    end
  end
endmodule

module state_memory(
    input logic         i_clk,
    input logic         i_rst_n,
    input logic [1:0]   i_next_state,
    output logic [1:0]  o_curr_state
  );

  parameter logic [1:0] S0 = 2'b00;
  parameter logic [1:0] S1 = 2'b01;
  parameter logic [1:0] S2 = 2'b10;
  parameter logic [1:0] S3 = 2'b11;

  always_ff @(posedge i_clk or negedge i_rst_n)
  begin
    if (!i_rst_n)
    begin
      o_curr_state <= S0;
    end
    else
    begin
      o_curr_state <= i_next_state;
    end
  end
endmodule

module output_logic(
    input logic [1:0]       i_curr_state,
    output logic            o_decision_bit
  );

  parameter logic [1:0] S0 = 2'b00;
  parameter logic [1:0] S1 = 2'b01;
  parameter logic [1:0] S2 = 2'b10;
  parameter logic [1:0] S3 = 2'b11;

  always_comb
  begin
    case(i_curr_state)
      S0, S1:
      begin
        o_decision_bit = 1'b0;
      end
      S2, S3:
      begin
        o_decision_bit = 1'b1;
      end
      default:
      begin
        o_decision_bit = 1'b0;
      end
    endcase
  end
endmodule

02_rtl/Compare_unit.sv
module Compare_unit(
    input logic [1:0] i_metric_path_0,  // A
    input logic [1:0] i_metric_path_1,  // B
    output logic o_compare_less      
);

// | A  | B  | C  |
// | 00 | 00 |  1 |
// | 00 | 01 |  1 |
// | 00 | 10 |  1 |
// | 00 | 11 |  1 |
// | 01 | 00 |  0 |
// | 01 | 01 |  1 |
// | 01 | 10 |  1 |
// | 01 | 11 |  1 |
// | 10 | 00 |  0 |
// | 10 | 01 |  0 |
// | 10 | 10 |  1 |
// | 10 | 11 |  1 |
// | 11 | 00 |  0 |
// | 11 | 01 |  0 |
// | 11 | 10 |  0 |
// | 11 | 11 |  1 |

    // Correct implementation
    assign o_compare_less = (~i_metric_path_0[0] & ~i_metric_path_0[1]) |
                            ( i_metric_path_1[0] &  i_metric_path_1[1]) |
                            (~i_metric_path_0[1] &  i_metric_path_1[0]) |
                            (~i_metric_path_0[1] &  i_metric_path_1[1]) |
                            (~i_metric_path_0[0] &  i_metric_path_1[1]) ;
endmodule

03_verif/SPMU/tb_spmu.sv
`timescale 1ns/1ps
module tb_spmu();

logic i_clk, i_rst_n, i_valid;
logic [1:0] w_PM_0, w_PM_1, w_PM_2, w_PM_3;
logic w_decision;

Survivor_path_memory_unit spmu(
    .i_clk       (i_clk),
    .i_rst_n     (i_rst_n),
    .i_valid     (i_valid),
    .i_PM_0      (w_PM_0),
    .i_PM_1      (w_PM_1),
    .i_PM_2      (w_PM_2),
    .i_PM_3      (w_PM_3),
    .o_decision  (w_decision)
);

always #5 i_clk = ~i_clk;

initial begin
    $dumpfile("tb_spmu.vcd");
    $dumpvars(0, tb_spmu);
end

initial begin
    i_clk = 1'b0;
    i_rst_n = 1'b0;
    i_valid = 1'b0;
    w_PM_0 = 2'b00;
    w_PM_1 = 2'b00;
    w_PM_2 = 2'b00;
    w_PM_3 = 2'b00;

    @(posedge i_clk);
    i_rst_n = 1'b1;
    $display("Time = %t \t| i_rst_n = %d \t| i_valid = %d \t| o_decision = %d \t|", 
             $time, i_rst_n, i_valid, w_decision);
    $display("PM_0 = %b \t| PM_1 = %b \t| PM_2 = %b \t| PM_3 = %b \t|",
             w_PM_0, w_PM_1, w_PM_2, w_PM_3);
    $display("=========================================");

    // case 1: S0 -> S0
    @(posedge i_clk);
    i_valid = 1'b1;
    w_PM_0 = 2'b00;
    w_PM_1 = 2'b01;
    w_PM_2 = 2'b10;
    w_PM_3 = 2'b11;
    #1;
    $display("case 1: S0 -> S0");
    $display("Time = %t \t| i_rst_n = %d \t| i_valid = %d \t| o_decision = %d \t|", 
             $time, i_rst_n, i_valid, w_decision);
    $display("PM_0 = %b \t| PM_1 = %b \t| PM_2 = %b \t| PM_3 = %b \t|",
             w_PM_0, w_PM_1, w_PM_2, w_PM_3);
    $display("-> %s", w_decision ? "FAIL" : "PASS");
    $display("=========================================");

    // case 2: S0 -> S2
    @(posedge i_clk);
    w_PM_0 = 2'b11;
    w_PM_1 = 2'b10;
    w_PM_2 = 2'b01;
    w_PM_3 = 2'b00;
    #1;
    $display("case 2: S0 -> S2");
    $display("Time = %t \t| i_rst_n = %d \t| i_valid = %d \t| o_decision = %d \t|", 
             $time, i_rst_n, i_valid, w_decision);
    $display("PM_0 = %b \t| PM_1 = %b \t| PM_2 = %b \t| PM_3 = %b \t|",
             w_PM_0, w_PM_1, w_PM_2, w_PM_3);
    $display("-> %s", w_decision ? "PASS" : "FAIL");
    $display("=========================================");

    // case 3: S2 -> S1
    @(posedge i_clk);
    w_PM_0 = 2'b10;
    w_PM_1 = 2'b00;
    w_PM_2 = 2'b00;
    w_PM_3 = 2'b01;
    #1;
    $display("case 3: S2 -> S1");
    $display("Time = %t \t| i_rst_n = %d \t| i_valid = %d \t| o_decision = %d \t|", 
             $time, i_rst_n, i_valid, w_decision);
    $display("PM_0 = %b \t| PM_1 = %b \t| PM_2 = %b \t| PM_3 = %b \t|",
             w_PM_0, w_PM_1, w_PM_2, w_PM_3);
    $display("-> %s", w_decision ? "FAIL" : "PASS");
    $display("=========================================");

    // case 4: S1 -> S2
    @(posedge i_clk);
    w_PM_0 = 2'b11;
    w_PM_1 = 2'b00;
    w_PM_2 = 2'b01;
    w_PM_3 = 2'b10;
    #1;
    $display("case 4: S1 -> S2");
    $display("Time = %t \t| i_rst_n = %d \t| i_valid = %d \t| o_decision = %d \t|", 
             $time, i_rst_n, i_valid, w_decision);
    $display("PM_0 = %b \t| PM_1 = %b \t| PM_2 = %b \t| PM_3 = %b \t|",
             w_PM_0, w_PM_1, w_PM_2, w_PM_3);
    $display("-> %s", w_decision ? "PASS" : "FAIL");
    $display("=========================================");

    // case 5: S2 -> S3
    @(posedge i_clk);
    w_PM_0 = 2'b01;
    w_PM_1 = 2'b10;
    w_PM_2 = 2'b11;
    w_PM_3 = 2'b00;
    #1;
    $display("case 5: S2 -> S3");
    $display("Time = %t \t| i_rst_n = %d \t| i_valid = %d \t| o_decision = %d \t|", 
             $time, i_rst_n, i_valid, w_decision);
    $display("PM_0 = %b \t| PM_1 = %b \t| PM_2 = %b \t| PM_3 = %b \t|",
             w_PM_0, w_PM_1, w_PM_2, w_PM_3);
    $display("-> %s", w_decision ? "PASS" : "FAIL");
    $display("=========================================");

    // case 6: S3 -> S3
    @(posedge i_clk);
    w_PM_0 = 2'b11;
    w_PM_1 = 2'b10;
    w_PM_2 = 2'b01;
    w_PM_3 = 2'b00;
    #1;
    $display("case 6: S3 -> S3");
    $display("Time = %t \t| i_rst_n = %d \t| i_valid = %d \t| o_decision = %d \t|", 
             $time, i_rst_n, i_valid, w_decision);
    $display("PM_0 = %b \t| PM_1 = %b \t| PM_2 = %b \t| PM_3 = %b \t|",
             w_PM_0, w_PM_1, w_PM_2, w_PM_3);
    $display("-> %s", w_decision ? "PASS" : "FAIL");
    $display("=========================================");

    // case 7: S3 -> S1
    @(posedge i_clk);
    w_PM_0 = 2'b11;
    w_PM_1 = 2'b00;
    w_PM_2 = 2'b01;
    w_PM_3 = 2'b10;
    #1;
    $display("case 7: S3 -> S1");
    $display("Time = %t \t| i_rst_n = %d \t| i_valid = %d \t| o_decision = %d \t|", 
             $time, i_rst_n, i_valid, w_decision);
    $display("PM_0 = %b \t| PM_1 = %b \t| PM_2 = %b \t| PM_3 = %b \t|",
             w_PM_0, w_PM_1, w_PM_2, w_PM_3);
    $display("-> %s", w_decision ? "FAIL" : "PASS");
    $display("=========================================");

    // case 8: S1 -> S0
    @(posedge i_clk);
    w_PM_0 = 2'b00;
    w_PM_1 = 2'b01;
    w_PM_2 = 2'b01;
    w_PM_3 = 2'b10;
    #1;
    $display("case 8: S1 -> S0");
    $display("Time = %t \t| i_rst_n = %d \t| i_valid = %d \t| o_decision = %d \t|", 
             $time, i_rst_n, i_valid, w_decision);
    $display("PM_0 = %b \t| PM_1 = %b \t| PM_2 = %b \t| PM_3 = %b \t|",
             w_PM_0, w_PM_1, w_PM_2, w_PM_3);
    $display("-> %s", w_decision ? "FAIL" : "PASS");
    $display("=========================================");

    #100;
    $display("Testbench completed successfully");
    $display("==================================");
    $finish;
end

endmodule

03_verif/SPMU/tb_spmu.vcd
$version Generated by VerilatedVcd $end
$timescale 1ps $end
 $scope module TOP $end
  $scope module tb_spmu $end
   $var wire 1 + i_clk $end
   $var wire 1 # i_rst_n $end
   $var wire 1 $ i_valid $end
   $var wire 2 % w_PM_0 [1:0] $end
   $var wire 2 & w_PM_1 [1:0] $end
   $var wire 2 ' w_PM_2 [1:0] $end
   $var wire 2 ( w_PM_3 [1:0] $end
   $var wire 1 , w_decision $end
   $scope module spmu $end
    $var wire 1 + i_clk $end
    $var wire 1 # i_rst_n $end
    $var wire 1 $ i_valid $end
    $var wire 2 % i_PM_0 [1:0] $end
    $var wire 2 & i_PM_1 [1:0] $end
    $var wire 2 ' i_PM_2 [1:0] $end
    $var wire 2 ( i_PM_3 [1:0] $end
    $var wire 1 , o_decision $end
    $var wire 1 ) w_compare_0 $end
    $var wire 1 * w_compare_1 $end
    $scope module CP0 $end
     $var wire 2 % i_metric_path_0 [1:0] $end
     $var wire 2 ' i_metric_path_1 [1:0] $end
     $var wire 1 ) o_compare_less $end
    $upscope $end
    $scope module CP1 $end
     $var wire 2 & i_metric_path_0 [1:0] $end
     $var wire 2 ( i_metric_path_1 [1:0] $end
     $var wire 1 * o_compare_less $end
    $upscope $end
    $scope module u_state_machine $end
     $var wire 1 + i_clk $end
     $var wire 1 # i_rst_n $end
     $var wire 1 $ i_valid $end
     $var wire 1 ) i_compare_0 $end
     $var wire 1 * i_compare_1 $end
     $var wire 1 , o_decision $end
     $var wire 2 / S0 [1:0] $end
     $var wire 2 0 S1 [1:0] $end
     $var wire 2 1 S2 [1:0] $end
     $var wire 2 2 S3 [1:0] $end
     $var wire 2 - state [1:0] $end
     $var wire 2 . nstate [1:0] $end
     $scope module NSL $end
      $var wire 1 $ i_valid $end
      $var wire 1 ) i_compare_0 $end
      $var wire 1 * i_compare_1 $end
      $var wire 2 - i_pre_state [1:0] $end
      $var wire 2 . o_next_state [1:0] $end
      $var wire 2 / S0 [1:0] $end
      $var wire 2 0 S1 [1:0] $end
      $var wire 2 1 S2 [1:0] $end
      $var wire 2 2 S3 [1:0] $end
     $upscope $end
     $scope module OL $end
      $var wire 2 - i_curr_state [1:0] $end
      $var wire 1 , o_decision_bit $end
      $var wire 2 / S0 [1:0] $end
      $var wire 2 0 S1 [1:0] $end
      $var wire 2 1 S2 [1:0] $end
      $var wire 2 2 S3 [1:0] $end
     $upscope $end
     $scope module SM $end
      $var wire 1 + i_clk $end
      $var wire 1 # i_rst_n $end
      $var wire 2 . i_next_state [1:0] $end
      $var wire 2 - o_curr_state [1:0] $end
      $var wire 2 / S0 [1:0] $end
      $var wire 2 0 S1 [1:0] $end
      $var wire 2 1 S2 [1:0] $end
      $var wire 2 2 S3 [1:0] $end
     $upscope $end
    $upscope $end
   $upscope $end
  $upscope $end
 $upscope $end
$enddefinitions $end


#0
0#
0$
b00 %
b00 &
b00 '
b00 (
1)
1*
0+
0,
b00 -
b00 .
b00 /
b01 0
b10 1
b11 2
#5000
1#
1+
#10000
0+
#15000
1$
b01 &
b10 '
b11 (
1+
#16000
#20000
0+
#25000
b11 %
b10 &
b01 '
b00 (
0)
0*
1+
1,
b10 -
b11 .
#26000
#30000
0+
#35000
b10 %
b00 &
b00 '
b01 (
1*
1+
0,
b01 -
b10 .
#36000
#40000
0+
#45000
b11 %
b01 '
b10 (
1+
1,
b10 -
b01 .
#46000
#50000
0+
#55000
b01 %
b10 &
b11 '
b00 (
1)
0*
1+
b11 -
b11 .
#56000
#60000
0+
#65000
b11 %
b01 '
0)
1+
#66000
#70000
0+
#75000
b00 &
b10 (
1*
1+
0,
b01 -
b10 .
#76000
#80000
0+
#85000
b00 %
b01 &
1)
1+
b00 -
b00 .
