02_rtl/Hex_to_7seg.sv
module Hex_to_7seg #(
    parameter SIZE_DATA = 4,
    parameter SIZE_7SEG = 7
)(
    input  logic                     i_en_hex   ,  
    input  logic [SIZE_DATA-1:0]     i_data     ,  
    output logic [SIZE_7SEG-1:0]     o_HEX      
);

    logic [SIZE_7SEG-1:0] seg;

    always @(*) begin
        case (i_data)
            4'h0:    seg = 7'b1000000;  // 0
            4'h1:    seg = 7'b1111001;  // 1
            4'h2:    seg = 7'b0100100;  // 2
            4'h3:    seg = 7'b0110000;  // 3
            4'h4:    seg = 7'b0011001;  // 4
            4'h5:    seg = 7'b0010010;  // 5
            4'h6:    seg = 7'b0000010;  // 6
            4'h7:    seg = 7'b1111000;  // 7
            4'h8:    seg = 7'b0000000;  // 8
            4'h9:    seg = 7'b0010000;  // 9
            4'hA:    seg = 7'b0001000;  // A
            4'hB:    seg = 7'b0000011;  // b
            4'hC:    seg = 7'b1000110;  // C
            4'hD:    seg = 7'b0100001;  // d
            4'hE:    seg = 7'b0000110;  // E
            4'hF:    seg = 7'b0001110;  // F
            default: seg = 7'b1111111;  // Default: all segments off
        endcase
    end

    assign o_HEX = (i_en_hex) ? seg : 7'b1111111;

endmodule

03_verif/HEX_TO_7SEG/tb_Hex_to_7seg.sv
module tb_Hex_to_7seg();

    // Test signals
    logic i_en_hex;
    logic [3:0] i_data;
    logic [7:0] o_HEX;

    // Instantiate DUT with 8-bit data size
    Hex_to_7seg #(.SIZE_DATA(8)) dut (
        .i_en_hex(i_en_hex),
        .i_data({4'b0, i_data}),  // Pad with zeros for 8-bit input
        .o_HEX(o_HEX)
    );

    // VCD file dumping
    initial begin
        $dumpfile("tb_Hex_to_7seg.vcd");
        $dumpvars(0, tb_Hex_to_7seg);
    end

    // Stimulus and verification
    initial begin
        // Test 1: Disabled module - all segments should be off
        i_en_hex = 0;
        i_data = 4'h0;
        #10;
        if (o_HEX !== 8'hFF) 
            $display("Error (Disabled): Expected 8'hFF, got %h", o_HEX);
        else 
            $display("Pass: Disabled - All segments off");

        // Test 2: Enable module and verify all hex values
        i_en_hex = 1;
        for (int i = 0; i < 16; i++) begin
            i_data = i;
            #10;
            
            // Expected values for common anode display
            case (i_data)
                4'h0: check_output(8'h40, "0");
                4'h1: check_output(8'h79, "1");
                4'h2: check_output(8'h24, "2");
                4'h3: check_output(8'h30, "3");
                4'h4: check_output(8'h19, "4");
                4'h5: check_output(8'h12, "5");
                4'h6: check_output(8'h02, "6");
                4'h7: check_output(8'h78, "7");
                4'h8: check_output(8'h00, "8");
                4'h9: check_output(8'h10, "9");
                4'hA: check_output(8'h08, "A");
                4'hB: check_output(8'h03, "b");
                4'hC: check_output(8'h46, "C");
                4'hD: check_output(8'h21, "d");
                4'hE: check_output(8'h06, "E");
                4'hF: check_output(8'h0E, "F");
            endcase
        end

        // Test 3: Disable module again
        i_en_hex = 0;
        i_data = 4'hF;  // Any data value
        #10;
        if (o_HEX !== 8'hFF) 
            $display("Error (Re-Disable): Expected 8'hFF, got %h", o_HEX);
        else 
            $display("Pass: Re-Disable - All segments off");

        $display("\nAll tests completed!");
        $finish;
    end

    // Helper task for output verification
    task check_output(input logic [7:0] expected, input string char);
        if (o_HEX !== expected) begin
            $display("Hex %s (0x%h) - Expected: %b (%h), Got: %b (%h) -> FAIL",
                     char, i_data, expected, expected, o_HEX, o_HEX);
        end
        else begin
            $display("Hex %s (0x%h) - Output: %b -> PASS", 
                     char, i_data, o_HEX);
        end
    endtask

endmodule

03_verif/HEX_TO_7SEG/tb_Hex_to_7seg.vcd
$version Generated by VerilatedVcd $end
$timescale 1ps $end
 $scope module TOP $end
  $scope module tb_Hex_to_7seg $end
   $var wire 1 # i_en_hex $end
   $var wire 4 $ i_data [3:0] $end
   $var wire 8 % o_HEX [7:0] $end
   $scope module dut $end
    $var wire 32 * SIZE_DATA [31:0] $end
    $var wire 32 + SIZE_7SEG [31:0] $end
    $var wire 1 # i_en_hex $end
    $var wire 8 & i_data [7:0] $end
    $var wire 7 ' o_HEX [6:0] $end
    $var wire 7 ( seg [6:0] $end
   $upscope $end
   $scope module unnamedblk1 $end
    $var wire 32 ) i [31:0] $end
   $upscope $end
  $upscope $end
 $upscope $end
$enddefinitions $end


#0
0#
b0000 $
b01111111 %
b00000000 &
b1111111 '
b1000000 (
b00000000000000000000000000000000 )
b00000000000000000000000000001000 *
b00000000000000000000000000000111 +
#10
1#
b01000000 %
b1000000 '
#20
b0001 $
b01111001 %
b00000001 &
b1111001 '
b1111001 (
b00000000000000000000000000000001 )
#30
b0010 $
b00100100 %
b00000010 &
b0100100 '
b0100100 (
b00000000000000000000000000000010 )
#40
b0011 $
b00110000 %
b00000011 &
b0110000 '
b0110000 (
b00000000000000000000000000000011 )
#50
b0100 $
b00011001 %
b00000100 &
b0011001 '
b0011001 (
b00000000000000000000000000000100 )
#60
b0101 $
b00010010 %
b00000101 &
b0010010 '
b0010010 (
b00000000000000000000000000000101 )
#70
b0110 $
b00000010 %
b00000110 &
b0000010 '
b0000010 (
b00000000000000000000000000000110 )
#80
b0111 $
b01111000 %
b00000111 &
b1111000 '
b1111000 (
b00000000000000000000000000000111 )
#90
b1000 $
b00000000 %
b00001000 &
b0000000 '
b0000000 (
b00000000000000000000000000001000 )
#100
b1001 $
b00010000 %
b00001001 &
b0010000 '
b0010000 (
b00000000000000000000000000001001 )
#110
b1010 $
b00001000 %
b00001010 &
b0001000 '
b0001000 (
b00000000000000000000000000001010 )
#120
b1011 $
b00000011 %
b00001011 &
b0000011 '
b0000011 (
b00000000000000000000000000001011 )
#130
b1100 $
b01000110 %
b00001100 &
b1000110 '
b1000110 (
b00000000000000000000000000001100 )
#140
b1101 $
b00100001 %
b00001101 &
b0100001 '
b0100001 (
b00000000000000000000000000001101 )
#150
b1110 $
b00000110 %
b00001110 &
b0000110 '
b0000110 (
b00000000000000000000000000001110 )
#160
b1111 $
b00001110 %
b00001111 &
b0001110 '
b0001110 (
b00000000000000000000000000001111 )
#170
0#
b01111111 %
b1111111 '
b00000000000000000000000000010000 )
