02_rtl/baud_generator.sv
////////////////////////////////////////////////////////////////////////////
// Filename      : baud_generator.sv
// Description   : baud rate generator
// Author        : Noname_29_lnin
// i_bdr_value = FREQ / (BAUDRATE * 16) - 1
////////////////////////////////////////////////////////////////////////////
module baud_generator #(
    parameter SIZE_BAUD      = 24 // 3byte
    // parameter BAUDRATE_VALUE = 325
)(
    input wire i_clk       , // clock for CPU
    input wire i_rst_n     , // active low reset
    input wire [SIZE_BAUD-1:0] i_baud_rate,
    output wire o_stick     // baud rate signal
);
reg [SIZE_BAUD-1 : 0] bdr_count, n_bdr_count; // baud rate counter

assign o_stick = (bdr_count == i_baud_rate) ? 1'b1 : 1'b0; // baud rate signal

assign n_bdr_count = (o_stick) ? '0 : (bdr_count + 1'b1); // baud rate counter
always_ff @( posedge i_clk or negedge i_rst_n ) begin : proc_divider_baud
    if(~i_rst_n)
        bdr_count <= '0;
    else
        bdr_count <= n_bdr_count;
end
endmodule

03_verif/Baud_generator/tb_baud_generator.sv
`timescale 1us / 1ps
module tb_baud_generator;

logic w_clk, w_rst_n;
logic w_stick;

baud_generator #(
    .SIZE_BAUD      (24) // 3byte
) baudrate (
    .i_clk          (w_clk),    // clock for CPU
    .i_rst_n        (w_rst_n),  // active low reset
    .i_baud_rate    (24'd325),
    .o_stick        (w_stick)   // baud rate signal
);

always #25 w_clk = ~w_clk; // clock generation

initial begin
    $dumpfile("tb_baud_generator.vcd");
    $dumpvars(0, tb_baud_generator);
end

initial begin
    w_clk   = 1'b0;
    w_rst_n = 1'b0;
    #50 w_rst_n = 1'b1; // release reset
    $display("Reset at time: %t", $time);
    wait(w_stick == 1'b1); // wait for baud rate signal
    $display("Baud rate signal is HIGH at time %t", $time);
    #100 $finish; // finish simulation
end

endmodule

03_verif/Baud_generator/tb_baud_generator.vcd
$version Generated by VerilatedVcd $end
$timescale 1ps $end
 $scope module TOP $end
  $scope module tb_baud_generator $end
   $var wire 1 & w_clk $end
   $var wire 1 ' w_rst_n $end
   $var wire 1 # w_stick $end
   $scope module baudrate $end
    $var wire 32 ( SIZE_BAUD [31:0] $end
    $var wire 1 & i_clk $end
    $var wire 1 ' i_rst_n $end
    $var wire 24 ) i_baud_rate [23:0] $end
    $var wire 1 # o_stick $end
    $var wire 24 $ bdr_count [23:0] $end
    $var wire 24 % n_bdr_count [23:0] $end
   $upscope $end
  $upscope $end
 $upscope $end
$enddefinitions $end


#0
0#
b000000000000000000000000 $
b000000000000000000000001 %
0&
0'
b00000000000000000000000000011000 (
b000000000000000101000101 )
#25000000
1&
#50000000
0&
1'
#75000000
b000000000000000000000001 $
b000000000000000000000010 %
1&
#100000000
0&
#125000000
b000000000000000000000010 $
b000000000000000000000011 %
1&
#150000000
0&
#175000000
b000000000000000000000011 $
b000000000000000000000100 %
1&
#200000000
0&
#225000000
b000000000000000000000100 $
b000000000000000000000101 %
1&
#250000000
0&
#275000000
b000000000000000000000101 $
b000000000000000000000110 %
1&
#300000000
0&
#325000000
b000000000000000000000110 $
b000000000000000000000111 %
1&
#350000000
0&
#375000000
b000000000000000000000111 $
b000000000000000000001000 %
1&
#400000000
0&
#425000000
b000000000000000000001000 $
b000000000000000000001001 %
1&
#450000000
0&
#475000000
b000000000000000000001001 $
b000000000000000000001010 %
1&
#500000000
0&
#525000000
b000000000000000000001010 $
b000000000000000000001011 %
1&
#550000000
0&
#575000000
b000000000000000000001011 $
b000000000000000000001100 %
1&
#600000000
0&
#625000000
b000000000000000000001100 $
b000000000000000000001101 %
1&
#650000000
0&
#675000000
b000000000000000000001101 $
b000000000000000000001110 %
1&
#700000000
0&
#725000000
b000000000000000000001110 $
b000000000000000000001111 %
1&
#750000000
0&
#775000000
b000000000000000000001111 $
b000000000000000000010000 %
1&
#800000000
0&
#825000000
b000000000000000000010000 $
b000000000000000000010001 %
1&
#850000000
0&
#875000000
b000000000000000000010001 $
b000000000000000000010010 %
1&
#900000000
0&
#925000000
b000000000000000000010010 $
b000000000000000000010011 %
1&
#950000000
0&
#975000000
b000000000000000000010011 $
b000000000000000000010100 %
1&
#1000000000
0&
#1025000000
b000000000000000000010100 $
b000000000000000000010101 %
1&
#1050000000
0&
#1075000000
b000000000000000000010101 $
b000000000000000000010110 %
1&
#1100000000
0&
#1125000000
b000000000000000000010110 $
b000000000000000000010111 %
1&
#1150000000
0&
#1175000000
b000000000000000000010111 $
b000000000000000000011000 %
1&
#1200000000
0&
#1225000000
b000000000000000000011000 $
b000000000000000000011001 %
1&
#1250000000
0&
#1275000000
b000000000000000000011001 $
b000000000000000000011010 %
1&
#1300000000
0&
#1325000000
b000000000000000000011010 $
b000000000000000000011011 %
1&
#1350000000
0&
#1375000000
b000000000000000000011011 $
b000000000000000000011100 %
1&
#1400000000
0&
#1425000000
b000000000000000000011100 $
b000000000000000000011101 %
1&
#1450000000
0&
#1475000000
b000000000000000000011101 $
b000000000000000000011110 %
1&
#1500000000
0&
#1525000000
b000000000000000000011110 $
b000000000000000000011111 %
1&
#1550000000
0&
#1575000000
b000000000000000000011111 $
b000000000000000000100000 %
1&
#1600000000
0&
#1625000000
b000000000000000000100000 $
b000000000000000000100001 %
1&
#1650000000
0&
#1675000000
b000000000000000000100001 $
b000000000000000000100010 %
1&
#1700000000
0&
#1725000000
b000000000000000000100010 $
b000000000000000000100011 %
1&
#1750000000
0&
#1775000000
b000000000000000000100011 $
b000000000000000000100100 %
1&
#1800000000
0&
#1825000000
b000000000000000000100100 $
b000000000000000000100101 %
1&
#1850000000
0&
#1875000000
b000000000000000000100101 $
b000000000000000000100110 %
1&
#1900000000
0&
#1925000000
b000000000000000000100110 $
b000000000000000000100111 %
1&
#1950000000
0&
#1975000000
b000000000000000000100111 $
b000000000000000000101000 %
1&
#2000000000
0&
#2025000000
b000000000000000000101000 $
b000000000000000000101001 %
1&
#2050000000
0&
#2075000000
b000000000000000000101001 $
b000000000000000000101010 %
1&
#2100000000
0&
#2125000000
b000000000000000000101010 $
b000000000000000000101011 %
1&
#2150000000
0&
#2175000000
b000000000000000000101011 $
b000000000000000000101100 %
1&
#2200000000
0&
#2225000000
b000000000000000000101100 $
b000000000000000000101101 %
1&
#2250000000
0&
#2275000000
b000000000000000000101101 $
b000000000000000000101110 %
1&
#2300000000
0&
#2325000000
b000000000000000000101110 $
b000000000000000000101111 %
1&
#2350000000
0&
#2375000000
b000000000000000000101111 $
b000000000000000000110000 %
1&
#2400000000
0&
#2425000000
b000000000000000000110000 $
b000000000000000000110001 %
1&
#2450000000
0&
#2475000000
b000000000000000000110001 $
b000000000000000000110010 %
1&
#2500000000
0&
#2525000000
b000000000000000000110010 $
b000000000000000000110011 %
1&
#2550000000
0&
#2575000000
b000000000000000000110011 $
b000000000000000000110100 %
1&
#2600000000
0&
#2625000000
b000000000000000000110100 $
b000000000000000000110101 %
1&
#2650000000
0&
#2675000000
b000000000000000000110101 $
b000000000000000000110110 %
1&
#2700000000
0&
#2725000000
b000000000000000000110110 $
b000000000000000000110111 %
1&
#2750000000
0&
#2775000000
b000000000000000000110111 $
b000000000000000000111000 %
1&
#2800000000
0&
#2825000000
b000000000000000000111000 $
b000000000000000000111001 %
1&
#2850000000
0&
#2875000000
b000000000000000000111001 $
b000000000000000000111010 %
1&
#2900000000
0&
#2925000000
b000000000000000000111010 $
b000000000000000000111011 %
1&
#2950000000
0&
#2975000000
b000000000000000000111011 $
b000000000000000000111100 %
1&
#3000000000
0&
#3025000000
b000000000000000000111100 $
b000000000000000000111101 %
1&
#3050000000
0&
#3075000000
b000000000000000000111101 $
b000000000000000000111110 %
1&
#3100000000
0&
#3125000000
b000000000000000000111110 $
b000000000000000000111111 %
1&
#3150000000
0&
#3175000000
b000000000000000000111111 $
b000000000000000001000000 %
1&
#3200000000
0&
#3225000000
b000000000000000001000000 $
b000000000000000001000001 %
1&
#3250000000
0&
#3275000000
b000000000000000001000001 $
b000000000000000001000010 %
1&
#3300000000
0&
#3325000000
b000000000000000001000010 $
b000000000000000001000011 %
1&
#3350000000
0&
#3375000000
b000000000000000001000011 $
b000000000000000001000100 %
1&
#3400000000
0&
#3425000000
b000000000000000001000100 $
b000000000000000001000101 %
1&
#3450000000
0&
#3475000000
b000000000000000001000101 $
b000000000000000001000110 %
1&
#3500000000
0&
#3525000000
b000000000000000001000110 $
b000000000000000001000111 %
1&
#3550000000
0&
#3575000000
b000000000000000001000111 $
b000000000000000001001000 %
1&
#3600000000
0&
#3625000000
b000000000000000001001000 $
b000000000000000001001001 %
1&
#3650000000
0&
#3675000000
b000000000000000001001001 $
b000000000000000001001010 %
1&
#3700000000
0&
#3725000000
b000000000000000001001010 $
b000000000000000001001011 %
1&
#3750000000
0&
#3775000000
b000000000000000001001011 $
b000000000000000001001100 %
1&
#3800000000
0&
#3825000000
b000000000000000001001100 $
b000000000000000001001101 %
1&
#3850000000
0&
#3875000000
b000000000000000001001101 $
b000000000000000001001110 %
1&
#3900000000
0&
#3925000000
b000000000000000001001110 $
b000000000000000001001111 %
1&
#3950000000
0&
#3975000000
b000000000000000001001111 $
b000000000000000001010000 %
1&
#4000000000
0&
#4025000000
b000000000000000001010000 $
b000000000000000001010001 %
1&
#4050000000
0&
#4075000000
b000000000000000001010001 $
b000000000000000001010010 %
1&
#4100000000
0&
#4125000000
b000000000000000001010010 $
b000000000000000001010011 %
1&
#4150000000
0&
#4175000000
b000000000000000001010011 $
b000000000000000001010100 %
1&
#4200000000
0&
#4225000000
b000000000000000001010100 $
b000000000000000001010101 %
1&
#4250000000
0&
#4275000000
b000000000000000001010101 $
b000000000000000001010110 %
1&
#4300000000
0&
#4325000000
b000000000000000001010110 $
b000000000000000001010111 %
1&
#4350000000
0&
#4375000000
b000000000000000001010111 $
b000000000000000001011000 %
1&
#4400000000
0&
#4425000000
b000000000000000001011000 $
b000000000000000001011001 %
1&
#4450000000
0&
#4475000000
b000000000000000001011001 $
b000000000000000001011010 %
1&
#4500000000
0&
#4525000000
b000000000000000001011010 $
b000000000000000001011011 %
1&
#4550000000
0&
#4575000000
b000000000000000001011011 $
b000000000000000001011100 %
1&
#4600000000
0&
#4625000000
b000000000000000001011100 $
b000000000000000001011101 %
1&
#4650000000
0&
#4675000000
b000000000000000001011101 $
b000000000000000001011110 %
1&
#4700000000
0&
#4725000000
b000000000000000001011110 $
b000000000000000001011111 %
1&
#4750000000
0&
#4775000000
b000000000000000001011111 $
b000000000000000001100000 %
1&
#4800000000
0&
#4825000000
b000000000000000001100000 $
b000000000000000001100001 %
1&
#4850000000
0&
#4875000000
b000000000000000001100001 $
b000000000000000001100010 %
1&
#4900000000
0&
#4925000000
b000000000000000001100010 $
b000000000000000001100011 %
1&
#4950000000
0&
#4975000000
b000000000000000001100011 $
b000000000000000001100100 %
1&
#5000000000
0&
#5025000000
b000000000000000001100100 $
b000000000000000001100101 %
1&
#5050000000
0&
#5075000000
b000000000000000001100101 $
b000000000000000001100110 %
1&
#5100000000
0&
#5125000000
b000000000000000001100110 $
b000000000000000001100111 %
1&
#5150000000
0&
#5175000000
b000000000000000001100111 $
b000000000000000001101000 %
1&
#5200000000
0&
#5225000000
b000000000000000001101000 $
b000000000000000001101001 %
1&
#5250000000
0&
#5275000000
b000000000000000001101001 $
b000000000000000001101010 %
1&
#5300000000
0&
#5325000000
b000000000000000001101010 $
b000000000000000001101011 %
1&
#5350000000
0&
#5375000000
b000000000000000001101011 $
b000000000000000001101100 %
1&
#5400000000
0&
#5425000000
b000000000000000001101100 $
b000000000000000001101101 %
1&
#5450000000
0&
#5475000000
b000000000000000001101101 $
b000000000000000001101110 %
1&
#5500000000
0&
#5525000000
b000000000000000001101110 $
b000000000000000001101111 %
1&
#5550000000
0&
#5575000000
b000000000000000001101111 $
b000000000000000001110000 %
1&
#5600000000
0&
#5625000000
b000000000000000001110000 $
b000000000000000001110001 %
1&
#5650000000
0&
#5675000000
b000000000000000001110001 $
b000000000000000001110010 %
1&
#5700000000
0&
#5725000000
b000000000000000001110010 $
b000000000000000001110011 %
1&
#5750000000
0&
#5775000000
b000000000000000001110011 $
b000000000000000001110100 %
1&
#5800000000
0&
#5825000000
b000000000000000001110100 $
b000000000000000001110101 %
1&
#5850000000
0&
#5875000000
b000000000000000001110101 $
b000000000000000001110110 %
1&
#5900000000
0&
#5925000000
b000000000000000001110110 $
b000000000000000001110111 %
1&
#5950000000
0&
#5975000000
b000000000000000001110111 $
b000000000000000001111000 %
1&
#6000000000
0&
#6025000000
b000000000000000001111000 $
b000000000000000001111001 %
1&
#6050000000
0&
#6075000000
b000000000000000001111001 $
b000000000000000001111010 %
1&
#6100000000
0&
#6125000000
b000000000000000001111010 $
b000000000000000001111011 %
1&
#6150000000
0&
#6175000000
b000000000000000001111011 $
b000000000000000001111100 %
1&
#6200000000
0&
#6225000000
b000000000000000001111100 $
b000000000000000001111101 %
1&
#6250000000
0&
#6275000000
b000000000000000001111101 $
b000000000000000001111110 %
1&
#6300000000
0&
#6325000000
b000000000000000001111110 $
b000000000000000001111111 %
1&
#6350000000
0&
#6375000000
b000000000000000001111111 $
b000000000000000010000000 %
1&
#6400000000
0&
#6425000000
b000000000000000010000000 $
b000000000000000010000001 %
1&
#6450000000
0&
#6475000000
b000000000000000010000001 $
b000000000000000010000010 %
1&
#6500000000
0&
#6525000000
b000000000000000010000010 $
b000000000000000010000011 %
1&
#6550000000
0&
#6575000000
b000000000000000010000011 $
b000000000000000010000100 %
1&
#6600000000
0&
#6625000000
b000000000000000010000100 $
b000000000000000010000101 %
1&
#6650000000
0&
#6675000000
b000000000000000010000101 $
b000000000000000010000110 %
1&
#6700000000
0&
#6725000000
b000000000000000010000110 $
b000000000000000010000111 %
1&
#6750000000
0&
#6775000000
b000000000000000010000111 $
b000000000000000010001000 %
1&
#6800000000
0&
#6825000000
b000000000000000010001000 $
b000000000000000010001001 %
1&
#6850000000
0&
#6875000000
b000000000000000010001001 $
b000000000000000010001010 %
1&
#6900000000
0&
#6925000000
b000000000000000010001010 $
b000000000000000010001011 %
1&
#6950000000
0&
#6975000000
b000000000000000010001011 $
b000000000000000010001100 %
1&
#7000000000
0&
#7025000000
b000000000000000010001100 $
b000000000000000010001101 %
1&
#7050000000
0&
#7075000000
b000000000000000010001101 $
b000000000000000010001110 %
1&
#7100000000
0&
#7125000000
b000000000000000010001110 $
b000000000000000010001111 %
1&
#7150000000
0&
#7175000000
b000000000000000010001111 $
b000000000000000010010000 %
1&
#7200000000
0&
#7225000000
b000000000000000010010000 $
b000000000000000010010001 %
1&
#7250000000
0&
#7275000000
b000000000000000010010001 $
b000000000000000010010010 %
1&
#7300000000
0&
#7325000000
b000000000000000010010010 $
b000000000000000010010011 %
1&
#7350000000
0&
#7375000000
b000000000000000010010011 $
b000000000000000010010100 %
1&
#7400000000
0&
#7425000000
b000000000000000010010100 $
b000000000000000010010101 %
1&
#7450000000
0&
#7475000000
b000000000000000010010101 $
b000000000000000010010110 %
1&
#7500000000
0&
#7525000000
b000000000000000010010110 $
b000000000000000010010111 %
1&
#7550000000
0&
#7575000000
b000000000000000010010111 $
b000000000000000010011000 %
1&
#7600000000
0&
#7625000000
b000000000000000010011000 $
b000000000000000010011001 %
1&
#7650000000
0&
#7675000000
b000000000000000010011001 $
b000000000000000010011010 %
1&
#7700000000
0&
#7725000000
b000000000000000010011010 $
b000000000000000010011011 %
1&
#7750000000
0&
#7775000000
b000000000000000010011011 $
b000000000000000010011100 %
1&
#7800000000
0&
#7825000000
b000000000000000010011100 $
b000000000000000010011101 %
1&
#7850000000
0&
#7875000000
b000000000000000010011101 $
b000000000000000010011110 %
1&
#7900000000
0&
#7925000000
b000000000000000010011110 $
b000000000000000010011111 %
1&
#7950000000
0&
#7975000000
b000000000000000010011111 $
b000000000000000010100000 %
1&
#8000000000
0&
#8025000000
b000000000000000010100000 $
b000000000000000010100001 %
1&
#8050000000
0&
#8075000000
b000000000000000010100001 $
b000000000000000010100010 %
1&
#8100000000
0&
#8125000000
b000000000000000010100010 $
b000000000000000010100011 %
1&
#8150000000
0&
#8175000000
b000000000000000010100011 $
b000000000000000010100100 %
1&
#8200000000
0&
#8225000000
b000000000000000010100100 $
b000000000000000010100101 %
1&
#8250000000
0&
#8275000000
b000000000000000010100101 $
b000000000000000010100110 %
1&
#8300000000
0&
#8325000000
b000000000000000010100110 $
b000000000000000010100111 %
1&
#8350000000
0&
#8375000000
b000000000000000010100111 $
b000000000000000010101000 %
1&
#8400000000
0&
#8425000000
b000000000000000010101000 $
b000000000000000010101001 %
1&
#8450000000
0&
#8475000000
b000000000000000010101001 $
b000000000000000010101010 %
1&
#8500000000
0&
#8525000000
b000000000000000010101010 $
b000000000000000010101011 %
1&
#8550000000
0&
#8575000000
b000000000000000010101011 $
b000000000000000010101100 %
1&
#8600000000
0&
#8625000000
b000000000000000010101100 $
b000000000000000010101101 %
1&
#8650000000
0&
#8675000000
b000000000000000010101101 $
b000000000000000010101110 %
1&
#8700000000
0&
#8725000000
b000000000000000010101110 $
b000000000000000010101111 %
1&
#8750000000
0&
#8775000000
b000000000000000010101111 $
b000000000000000010110000 %
1&
#8800000000
0&
#8825000000
b000000000000000010110000 $
b000000000000000010110001 %
1&
#8850000000
0&
#8875000000
b000000000000000010110001 $
b000000000000000010110010 %
1&
#8900000000
0&
#8925000000
b000000000000000010110010 $
b000000000000000010110011 %
1&
#8950000000
0&
#8975000000
b000000000000000010110011 $
b000000000000000010110100 %
1&
#9000000000
0&
#9025000000
b000000000000000010110100 $
b000000000000000010110101 %
1&
#9050000000
0&
#9075000000
b000000000000000010110101 $
b000000000000000010110110 %
1&
#9100000000
0&
#9125000000
b000000000000000010110110 $
b000000000000000010110111 %
1&
#9150000000
0&
#9175000000
b000000000000000010110111 $
b000000000000000010111000 %
1&
#9200000000
0&
#9225000000
b000000000000000010111000 $
b000000000000000010111001 %
1&
#9250000000
0&
#9275000000
b000000000000000010111001 $
b000000000000000010111010 %
1&
#9300000000
0&
#9325000000
b000000000000000010111010 $
b000000000000000010111011 %
1&
#9350000000
0&
#9375000000
b000000000000000010111011 $
b000000000000000010111100 %
1&
#9400000000
0&
#9425000000
b000000000000000010111100 $
b000000000000000010111101 %
1&
#9450000000
0&
#9475000000
b000000000000000010111101 $
b000000000000000010111110 %
1&
#9500000000
0&
#9525000000
b000000000000000010111110 $
b000000000000000010111111 %
1&
#9550000000
0&
#9575000000
b000000000000000010111111 $
b000000000000000011000000 %
1&
#9600000000
0&
#9625000000
b000000000000000011000000 $
b000000000000000011000001 %
1&
#9650000000
0&
#9675000000
b000000000000000011000001 $
b000000000000000011000010 %
1&
#9700000000
0&
#9725000000
b000000000000000011000010 $
b000000000000000011000011 %
1&
#9750000000
0&
#9775000000
b000000000000000011000011 $
b000000000000000011000100 %
1&
#9800000000
0&
#9825000000
b000000000000000011000100 $
b000000000000000011000101 %
1&
#9850000000
0&
#9875000000
b000000000000000011000101 $
b000000000000000011000110 %
1&
#9900000000
0&
#9925000000
b000000000000000011000110 $
b000000000000000011000111 %
1&
#9950000000
0&
#9975000000
b000000000000000011000111 $
b000000000000000011001000 %
1&
#10000000000
0&
#10025000000
b000000000000000011001000 $
b000000000000000011001001 %
1&
#10050000000
0&
#10075000000
b000000000000000011001001 $
b000000000000000011001010 %
1&
#10100000000
0&
#10125000000
b000000000000000011001010 $
b000000000000000011001011 %
1&
#10150000000
0&
#10175000000
b000000000000000011001011 $
b000000000000000011001100 %
1&
#10200000000
0&
#10225000000
b000000000000000011001100 $
b000000000000000011001101 %
1&
#10250000000
0&
#10275000000
b000000000000000011001101 $
b000000000000000011001110 %
1&
#10300000000
0&
#10325000000
b000000000000000011001110 $
b000000000000000011001111 %
1&
#10350000000
0&
#10375000000
b000000000000000011001111 $
b000000000000000011010000 %
1&
#10400000000
0&
#10425000000
b000000000000000011010000 $
b000000000000000011010001 %
1&
#10450000000
0&
#10475000000
b000000000000000011010001 $
b000000000000000011010010 %
1&
#10500000000
0&
#10525000000
b000000000000000011010010 $
b000000000000000011010011 %
1&
#10550000000
0&
#10575000000
b000000000000000011010011 $
b000000000000000011010100 %
1&
#10600000000
0&
#10625000000
b000000000000000011010100 $
b000000000000000011010101 %
1&
#10650000000
0&
#10675000000
b000000000000000011010101 $
b000000000000000011010110 %
1&
#10700000000
0&
#10725000000
b000000000000000011010110 $
b000000000000000011010111 %
1&
#10750000000
0&
#10775000000
b000000000000000011010111 $
b000000000000000011011000 %
1&
#10800000000
0&
#10825000000
b000000000000000011011000 $
b000000000000000011011001 %
1&
#10850000000
0&
#10875000000
b000000000000000011011001 $
b000000000000000011011010 %
1&
#10900000000
0&
#10925000000
b000000000000000011011010 $
b000000000000000011011011 %
1&
#10950000000
0&
#10975000000
b000000000000000011011011 $
b000000000000000011011100 %
1&
#11000000000
0&
#11025000000
b000000000000000011011100 $
b000000000000000011011101 %
1&
#11050000000
0&
#11075000000
b000000000000000011011101 $
b000000000000000011011110 %
1&
#11100000000
0&
#11125000000
b000000000000000011011110 $
b000000000000000011011111 %
1&
#11150000000
0&
#11175000000
b000000000000000011011111 $
b000000000000000011100000 %
1&
#11200000000
0&
#11225000000
b000000000000000011100000 $
b000000000000000011100001 %
1&
#11250000000
0&
#11275000000
b000000000000000011100001 $
b000000000000000011100010 %
1&
#11300000000
0&
#11325000000
b000000000000000011100010 $
b000000000000000011100011 %
1&
#11350000000
0&
#11375000000
b000000000000000011100011 $
b000000000000000011100100 %
1&
#11400000000
0&
#11425000000
b000000000000000011100100 $
b000000000000000011100101 %
1&
#11450000000
0&
#11475000000
b000000000000000011100101 $
b000000000000000011100110 %
1&
#11500000000
0&
#11525000000
b000000000000000011100110 $
b000000000000000011100111 %
1&
#11550000000
0&
#11575000000
b000000000000000011100111 $
b000000000000000011101000 %
1&
#11600000000
0&
#11625000000
b000000000000000011101000 $
b000000000000000011101001 %
1&
#11650000000
0&
#11675000000
b000000000000000011101001 $
b000000000000000011101010 %
1&
#11700000000
0&
#11725000000
b000000000000000011101010 $
b000000000000000011101011 %
1&
#11750000000
0&
#11775000000
b000000000000000011101011 $
b000000000000000011101100 %
1&
#11800000000
0&
#11825000000
b000000000000000011101100 $
b000000000000000011101101 %
1&
#11850000000
0&
#11875000000
b000000000000000011101101 $
b000000000000000011101110 %
1&
#11900000000
0&
#11925000000
b000000000000000011101110 $
b000000000000000011101111 %
1&
#11950000000
0&
#11975000000
b000000000000000011101111 $
b000000000000000011110000 %
1&
#12000000000
0&
#12025000000
b000000000000000011110000 $
b000000000000000011110001 %
1&
#12050000000
0&
#12075000000
b000000000000000011110001 $
b000000000000000011110010 %
1&
#12100000000
0&
#12125000000
b000000000000000011110010 $
b000000000000000011110011 %
1&
#12150000000
0&
#12175000000
b000000000000000011110011 $
b000000000000000011110100 %
1&
#12200000000
0&
#12225000000
b000000000000000011110100 $
b000000000000000011110101 %
1&
#12250000000
0&
#12275000000
b000000000000000011110101 $
b000000000000000011110110 %
1&
#12300000000
0&
#12325000000
b000000000000000011110110 $
b000000000000000011110111 %
1&
#12350000000
0&
#12375000000
b000000000000000011110111 $
b000000000000000011111000 %
1&
#12400000000
0&
#12425000000
b000000000000000011111000 $
b000000000000000011111001 %
1&
#12450000000
0&
#12475000000
b000000000000000011111001 $
b000000000000000011111010 %
1&
#12500000000
0&
#12525000000
b000000000000000011111010 $
b000000000000000011111011 %
1&
#12550000000
0&
#12575000000
b000000000000000011111011 $
b000000000000000011111100 %
1&
#12600000000
0&
#12625000000
b000000000000000011111100 $
b000000000000000011111101 %
1&
#12650000000
0&
#12675000000
b000000000000000011111101 $
b000000000000000011111110 %
1&
#12700000000
0&
#12725000000
b000000000000000011111110 $
b000000000000000011111111 %
1&
#12750000000
0&
#12775000000
b000000000000000011111111 $
b000000000000000100000000 %
1&
#12800000000
0&
#12825000000
b000000000000000100000000 $
b000000000000000100000001 %
1&
#12850000000
0&
#12875000000
b000000000000000100000001 $
b000000000000000100000010 %
1&
#12900000000
0&
#12925000000
b000000000000000100000010 $
b000000000000000100000011 %
1&
#12950000000
0&
#12975000000
b000000000000000100000011 $
b000000000000000100000100 %
1&
#13000000000
0&
#13025000000
b000000000000000100000100 $
b000000000000000100000101 %
1&
#13050000000
0&
#13075000000
b000000000000000100000101 $
b000000000000000100000110 %
1&
#13100000000
0&
#13125000000
b000000000000000100000110 $
b000000000000000100000111 %
1&
#13150000000
0&
#13175000000
b000000000000000100000111 $
b000000000000000100001000 %
1&
#13200000000
0&
#13225000000
b000000000000000100001000 $
b000000000000000100001001 %
1&
#13250000000
0&
#13275000000
b000000000000000100001001 $
b000000000000000100001010 %
1&
#13300000000
0&
#13325000000
b000000000000000100001010 $
b000000000000000100001011 %
1&
#13350000000
0&
#13375000000
b000000000000000100001011 $
b000000000000000100001100 %
1&
#13400000000
0&
#13425000000
b000000000000000100001100 $
b000000000000000100001101 %
1&
#13450000000
0&
#13475000000
b000000000000000100001101 $
b000000000000000100001110 %
1&
#13500000000
0&
#13525000000
b000000000000000100001110 $
b000000000000000100001111 %
1&
#13550000000
0&
#13575000000
b000000000000000100001111 $
b000000000000000100010000 %
1&
#13600000000
0&
#13625000000
b000000000000000100010000 $
b000000000000000100010001 %
1&
#13650000000
0&
#13675000000
b000000000000000100010001 $
b000000000000000100010010 %
1&
#13700000000
0&
#13725000000
b000000000000000100010010 $
b000000000000000100010011 %
1&
#13750000000
0&
#13775000000
b000000000000000100010011 $
b000000000000000100010100 %
1&
#13800000000
0&
#13825000000
b000000000000000100010100 $
b000000000000000100010101 %
1&
#13850000000
0&
#13875000000
b000000000000000100010101 $
b000000000000000100010110 %
1&
#13900000000
0&
#13925000000
b000000000000000100010110 $
b000000000000000100010111 %
1&
#13950000000
0&
#13975000000
b000000000000000100010111 $
b000000000000000100011000 %
1&
#14000000000
0&
#14025000000
b000000000000000100011000 $
b000000000000000100011001 %
1&
#14050000000
0&
#14075000000
b000000000000000100011001 $
b000000000000000100011010 %
1&
#14100000000
0&
#14125000000
b000000000000000100011010 $
b000000000000000100011011 %
1&
#14150000000
0&
#14175000000
b000000000000000100011011 $
b000000000000000100011100 %
1&
#14200000000
0&
#14225000000
b000000000000000100011100 $
b000000000000000100011101 %
1&
#14250000000
0&
#14275000000
b000000000000000100011101 $
b000000000000000100011110 %
1&
#14300000000
0&
#14325000000
b000000000000000100011110 $
b000000000000000100011111 %
1&
#14350000000
0&
#14375000000
b000000000000000100011111 $
b000000000000000100100000 %
1&
#14400000000
0&
#14425000000
b000000000000000100100000 $
b000000000000000100100001 %
1&
#14450000000
0&
#14475000000
b000000000000000100100001 $
b000000000000000100100010 %
1&
#14500000000
0&
#14525000000
b000000000000000100100010 $
b000000000000000100100011 %
1&
#14550000000
0&
#14575000000
b000000000000000100100011 $
b000000000000000100100100 %
1&
#14600000000
0&
#14625000000
b000000000000000100100100 $
b000000000000000100100101 %
1&
#14650000000
0&
#14675000000
b000000000000000100100101 $
b000000000000000100100110 %
1&
#14700000000
0&
#14725000000
b000000000000000100100110 $
b000000000000000100100111 %
1&
#14750000000
0&
#14775000000
b000000000000000100100111 $
b000000000000000100101000 %
1&
#14800000000
0&
#14825000000
b000000000000000100101000 $
b000000000000000100101001 %
1&
#14850000000
0&
#14875000000
b000000000000000100101001 $
b000000000000000100101010 %
1&
#14900000000
0&
#14925000000
b000000000000000100101010 $
b000000000000000100101011 %
1&
#14950000000
0&
#14975000000
b000000000000000100101011 $
b000000000000000100101100 %
1&
#15000000000
0&
#15025000000
b000000000000000100101100 $
b000000000000000100101101 %
1&
#15050000000
0&
#15075000000
b000000000000000100101101 $
b000000000000000100101110 %
1&
#15100000000
0&
#15125000000
b000000000000000100101110 $
b000000000000000100101111 %
1&
#15150000000
0&
#15175000000
b000000000000000100101111 $
b000000000000000100110000 %
1&
#15200000000
0&
#15225000000
b000000000000000100110000 $
b000000000000000100110001 %
1&
#15250000000
0&
#15275000000
b000000000000000100110001 $
b000000000000000100110010 %
1&
#15300000000
0&
#15325000000
b000000000000000100110010 $
b000000000000000100110011 %
1&
#15350000000
0&
#15375000000
b000000000000000100110011 $
b000000000000000100110100 %
1&
#15400000000
0&
#15425000000
b000000000000000100110100 $
b000000000000000100110101 %
1&
#15450000000
0&
#15475000000
b000000000000000100110101 $
b000000000000000100110110 %
1&
#15500000000
0&
#15525000000
b000000000000000100110110 $
b000000000000000100110111 %
1&
#15550000000
0&
#15575000000
b000000000000000100110111 $
b000000000000000100111000 %
1&
#15600000000
0&
#15625000000
b000000000000000100111000 $
b000000000000000100111001 %
1&
#15650000000
0&
#15675000000
b000000000000000100111001 $
b000000000000000100111010 %
1&
#15700000000
0&
#15725000000
b000000000000000100111010 $
b000000000000000100111011 %
1&
#15750000000
0&
#15775000000
b000000000000000100111011 $
b000000000000000100111100 %
1&
#15800000000
0&
#15825000000
b000000000000000100111100 $
b000000000000000100111101 %
1&
#15850000000
0&
#15875000000
b000000000000000100111101 $
b000000000000000100111110 %
1&
#15900000000
0&
#15925000000
b000000000000000100111110 $
b000000000000000100111111 %
1&
#15950000000
0&
#15975000000
b000000000000000100111111 $
b000000000000000101000000 %
1&
#16000000000
0&
#16025000000
b000000000000000101000000 $
b000000000000000101000001 %
1&
#16050000000
0&
#16075000000
b000000000000000101000001 $
b000000000000000101000010 %
1&
#16100000000
0&
#16125000000
b000000000000000101000010 $
b000000000000000101000011 %
1&
#16150000000
0&
#16175000000
b000000000000000101000011 $
b000000000000000101000100 %
1&
#16200000000
0&
#16225000000
b000000000000000101000100 $
b000000000000000101000101 %
1&
#16250000000
0&
#16275000000
1#
b000000000000000101000101 $
b000000000000000000000000 %
1&
#16300000000
0&
#16325000000
0#
b000000000000000000000000 $
b000000000000000000000001 %
1&
#16350000000
0&
#16375000000
b000000000000000000000001 $
b000000000000000000000010 %
1&
